src/memory.sv
`timescale 1ns/1ps

// memory.sv
module memory #(
    parameter WORDS    = 128,               // 512 bytes
    parameter mem_init = ""
) (
    input  logic        clk,
    input  logic [31:0] address,
    input  logic [31:0] write_data,
    input  logic [3:0]  byte_enable,        // per-byte write mask (from load_store_decoder)
    input  logic        write_enable,
    input  logic        rst_n,
    output logic [31:0] read_data
);

/*
 * Word-addressed array, byte-enable granularity on writes.
 * Read is always a full 32-bit word; the reader module narrows it.
 * Misaligned word writes are a fatal simulation error.
 */

reg [31:0] mem [0:WORDS-1];

initial begin
    if (mem_init != "") begin
        $readmemh(mem_init, mem);
    end
end

// Write
always @(posedge clk) begin
    if (rst_n == 1'b0) begin
        for (int i = 0; i < WORDS; i++) begin
            mem[i] <= 32'b0;
        end
    end else if (write_enable) begin
        if (address[1:0] != 2'b00) begin
            $fatal("[MEMORY] Misaligned write at address 0x%08h — check your code.", address);
        end else begin
            // Selectively write only the enabled bytes
            for (int i = 0; i < 4; i++) begin
                if (byte_enable[i]) begin
                    /* verilator lint_off WIDTHTRUNC */
                    mem[address[31:2] & (WORDS-1)][(i*8)+:8] <= write_data[(i*8)+:8];
                    /* verilator lint_on WIDTHTRUNC */
                end
            end
        end
    end
end

// Read — combinational, full word; reader module handles narrowing
always_comb begin
    /* verilator lint_off WIDTHTRUNC */
    read_data = mem[address[31:2] & (WORDS-1)];
    /* verilator lint_on WIDTHTRUNC */
end

endmodule

tb/memory/dump.vcd
$version Generated by VerilatedVcd $end
$timescale 1ps $end
 $scope module $rootio $end
  $var wire 1 " clk $end
  $var wire 32 # address [31:0] $end
  $var wire 32 $ write_data [31:0] $end
  $var wire 4 % byte_enable [3:0] $end
  $var wire 1 & write_enable $end
  $var wire 1 ' rst_n $end
  $var wire 32 ( read_data [31:0] $end
 $upscope $end
 $scope module memory $end
  $var wire 32 0 WORDS [31:0] $end
  $var wire 8 1 mem_init [7:0] $end
  $var wire 1 ) clk $end
  $var wire 32 * address [31:0] $end
  $var wire 32 + write_data [31:0] $end
  $var wire 4 , byte_enable [3:0] $end
  $var wire 1 - write_enable $end
  $var wire 1 . rst_n $end
  $var wire 32 / read_data [31:0] $end
 $upscope $end
$enddefinitions $end


#0
1"
b00000000000000000000000000000000 #
b00000000000000000000000000000000 $
b0000 %
0&
1'
b00000000000000000000000000000000 (
1)
b00000000000000000000000000000000 *
b00000000000000000000000000000000 +
b0000 ,
0-
1.
b00000000000000000000000000000000 /
b00000000000000000000000010000000 0
b00000000 1
#500
0"
0)
#1000
1"
1)
#1500
0"
0)
#2000
1"
b00000000000000000000000000000100 #
1)
b00000000000000000000000000000100 *
#2500
0"
0)
#3000
1"
b00000000000000000000000000001000 #
1)
b00000000000000000000000000001000 *
#3500
0"
0)
#4000
1"
b00000000000000000000000000001100 #
1)
b00000000000000000000000000001100 *
#4500
0"
0)
#5000
1"
b00000000000000000000000000010000 #
1)
b00000000000000000000000000010000 *
#5500
0"
0)
#6000
1"
b00000000000000000000000000010100 #
1)
b00000000000000000000000000010100 *
#6500
0"
0)
#7000
1"
b00000000000000000000000000011000 #
1)
b00000000000000000000000000011000 *
#7500
0"
0)
#8000
1"
b00000000000000000000000000011100 #
1)
b00000000000000000000000000011100 *
#8500
0"
0)
#9000
1"
b00000000000000000000000000100000 #
1)
b00000000000000000000000000100000 *
#9500
0"
0)
#10000
1"
b00000000000000000000000000100100 #
1)
b00000000000000000000000000100100 *
#10500
0"
0)
#11000
1"
b00000000000000000000000000101000 #
1)
b00000000000000000000000000101000 *
#11500
0"
0)
#12000
1"
b00000000000000000000000000101100 #
1)
b00000000000000000000000000101100 *
#12500
0"
0)
#13000
1"
b00000000000000000000000000110000 #
1)
b00000000000000000000000000110000 *
#13500
0"
0)
#14000
1"
b00000000000000000000000000110100 #
1)
b00000000000000000000000000110100 *
#14500
0"
0)
#15000
1"
b00000000000000000000000000111000 #
1)
b00000000000000000000000000111000 *
#15500
0"
0)
#16000
1"
b00000000000000000000000000111100 #
1)
b00000000000000000000000000111100 *
#16500
0"
0)
#17000
1"
b00000000000000000000000001000000 #
1)
b00000000000000000000000001000000 *
#17500
0"
0)
#18000
1"
b00000000000000000000000001000100 #
1)
b00000000000000000000000001000100 *
#18500
0"
0)
#19000
1"
b00000000000000000000000001001000 #
1)
b00000000000000000000000001001000 *
#19500
0"
0)
#20000
1"
b00000000000000000000000001001100 #
1)
b00000000000000000000000001001100 *
#20500
0"
0)
#21000
1"
b00000000000000000000000001010000 #
1)
b00000000000000000000000001010000 *
#21500
0"
0)
#22000
1"
b00000000000000000000000001010100 #
1)
b00000000000000000000000001010100 *
#22500
0"
0)
#23000
1"
b00000000000000000000000001011000 #
1)
b00000000000000000000000001011000 *
#23500
0"
0)
#24000
1"
b00000000000000000000000001011100 #
1)
b00000000000000000000000001011100 *
#24500
0"
0)
#25000
1"
b00000000000000000000000001100000 #
1)
b00000000000000000000000001100000 *
#25500
0"
0)
#26000
1"
b00000000000000000000000001100100 #
1)
b00000000000000000000000001100100 *
#26500
0"
0)
#27000
1"
b00000000000000000000000001101000 #
1)
b00000000000000000000000001101000 *
#27500
0"
0)
#28000
1"
b00000000000000000000000001101100 #
1)
b00000000000000000000000001101100 *
#28500
0"
0)
#29000
1"
b00000000000000000000000001110000 #
1)
b00000000000000000000000001110000 *
#29500
0"
0)
#30000
1"
b00000000000000000000000001110100 #
1)
b00000000000000000000000001110100 *
#30500
0"
0)
#31000
1"
b00000000000000000000000001111000 #
1)
b00000000000000000000000001111000 *
#31500
0"
0)
#32000
1"
b00000000000000000000000001111100 #
1)
b00000000000000000000000001111100 *
#32500
0"
0)
#33000
1"
b00000000000000000000000010000000 #
1)
b00000000000000000000000010000000 *
#33500
0"
0)
#34000
1"
b00000000000000000000000010000100 #
1)
b00000000000000000000000010000100 *
#34500
0"
0)
#35000
1"
b00000000000000000000000010001000 #
1)
b00000000000000000000000010001000 *
#35500
0"
0)
#36000
1"
b00000000000000000000000010001100 #
1)
b00000000000000000000000010001100 *
#36500
0"
0)
#37000
1"
b00000000000000000000000010010000 #
1)
b00000000000000000000000010010000 *
#37500
0"
0)
#38000
1"
b00000000000000000000000010010100 #
1)
b00000000000000000000000010010100 *
#38500
0"
0)
#39000
1"
b00000000000000000000000010011000 #
1)
b00000000000000000000000010011000 *
#39500
0"
0)
#40000
1"
b00000000000000000000000010011100 #
1)
b00000000000000000000000010011100 *
#40500
0"
0)
#41000
1"
b00000000000000000000000010100000 #
1)
b00000000000000000000000010100000 *
#41500
0"
0)
#42000
1"
b00000000000000000000000010100100 #
1)
b00000000000000000000000010100100 *
#42500
0"
0)
#43000
1"
b00000000000000000000000010101000 #
1)
b00000000000000000000000010101000 *
#43500
0"
0)
#44000
1"
b00000000000000000000000010101100 #
1)
b00000000000000000000000010101100 *
#44500
0"
0)
#45000
1"
b00000000000000000000000010110000 #
1)
b00000000000000000000000010110000 *
#45500
0"
0)
#46000
1"
b00000000000000000000000010110100 #
1)
b00000000000000000000000010110100 *
#46500
0"
0)
#47000
1"
b00000000000000000000000010111000 #
1)
b00000000000000000000000010111000 *
#47500
0"
0)
#48000
1"
b00000000000000000000000010111100 #
1)
b00000000000000000000000010111100 *
#48500
0"
0)
#49000
1"
b00000000000000000000000011000000 #
1)
b00000000000000000000000011000000 *
#49500
0"
0)
#50000
1"
b00000000000000000000000011000100 #
1)
b00000000000000000000000011000100 *
#50500
0"
0)
#51000
1"
b00000000000000000000000011001000 #
1)
b00000000000000000000000011001000 *
#51500
0"
0)
#52000
1"
b00000000000000000000000011001100 #
1)
b00000000000000000000000011001100 *
#52500
0"
0)
#53000
1"
b00000000000000000000000011010000 #
1)
b00000000000000000000000011010000 *
#53500
0"
0)
#54000
1"
b00000000000000000000000011010100 #
1)
b00000000000000000000000011010100 *
#54500
0"
0)
#55000
1"
b00000000000000000000000011011000 #
1)
b00000000000000000000000011011000 *
#55500
0"
0)
#56000
1"
b00000000000000000000000011011100 #
1)
b00000000000000000000000011011100 *
#56500
0"
0)
#57000
1"
b00000000000000000000000011100000 #
1)
b00000000000000000000000011100000 *
#57500
0"
0)
#58000
1"
b00000000000000000000000011100100 #
1)
b00000000000000000000000011100100 *
#58500
0"
0)
#59000
1"
b00000000000000000000000011101000 #
1)
b00000000000000000000000011101000 *
#59500
0"
0)
#60000
1"
b00000000000000000000000011101100 #
1)
b00000000000000000000000011101100 *
#60500
0"
0)
#61000
1"
b00000000000000000000000011110000 #
1)
b00000000000000000000000011110000 *
#61500
0"
0)
#62000
1"
b00000000000000000000000011110100 #
1)
b00000000000000000000000011110100 *
#62500
0"
0)
#63000
1"
b00000000000000000000000011111000 #
1)
b00000000000000000000000011111000 *
#63500
0"
0)
#64000
1"
b00000000000000000000000011111100 #
1)
b00000000000000000000000011111100 *
#64500
0"
0)
#65000
1"
b00000000000000000000000100000000 #
1)
b00000000000000000000000100000000 *
#65500
0"
0)
#66000
1"
b00000000000000000000000100000100 #
1)
b00000000000000000000000100000100 *
#66500
0"
0)
#67000
1"
b00000000000000000000000100001000 #
1)
b00000000000000000000000100001000 *
#67500
0"
0)
#68000
1"
b00000000000000000000000100001100 #
1)
b00000000000000000000000100001100 *
#68500
0"
0)
#69000
1"
b00000000000000000000000100010000 #
1)
b00000000000000000000000100010000 *
#69500
0"
0)
#70000
1"
b00000000000000000000000100010100 #
1)
b00000000000000000000000100010100 *
#70500
0"
0)
#71000
1"
b00000000000000000000000100011000 #
1)
b00000000000000000000000100011000 *
#71500
0"
0)
#72000
1"
b00000000000000000000000100011100 #
1)
b00000000000000000000000100011100 *
#72500
0"
0)
#73000
1"
b00000000000000000000000100100000 #
1)
b00000000000000000000000100100000 *
#73500
0"
0)
#74000
1"
b00000000000000000000000100100100 #
1)
b00000000000000000000000100100100 *
#74500
0"
0)
#75000
1"
b00000000000000000000000100101000 #
1)
b00000000000000000000000100101000 *
#75500
0"
0)
#76000
1"
b00000000000000000000000100101100 #
1)
b00000000000000000000000100101100 *
#76500
0"
0)
#77000
1"
b00000000000000000000000100110000 #
1)
b00000000000000000000000100110000 *
#77500
0"
0)
#78000
1"
b00000000000000000000000100110100 #
1)
b00000000000000000000000100110100 *
#78500
0"
0)
#79000
1"
b00000000000000000000000100111000 #
1)
b00000000000000000000000100111000 *
#79500
0"
0)
#80000
1"
b00000000000000000000000100111100 #
1)
b00000000000000000000000100111100 *
#80500
0"
0)
#81000
1"
b00000000000000000000000101000000 #
1)
b00000000000000000000000101000000 *
#81500
0"
0)
#82000
1"
b00000000000000000000000101000100 #
1)
b00000000000000000000000101000100 *
#82500
0"
0)
#83000
1"
b00000000000000000000000101001000 #
1)
b00000000000000000000000101001000 *
#83500
0"
0)
#84000
1"
b00000000000000000000000101001100 #
1)
b00000000000000000000000101001100 *
#84500
0"
0)
#85000
1"
b00000000000000000000000101010000 #
1)
b00000000000000000000000101010000 *
#85500
0"
0)
#86000
1"
b00000000000000000000000101010100 #
1)
b00000000000000000000000101010100 *
#86500
0"
0)
#87000
1"
b00000000000000000000000101011000 #
1)
b00000000000000000000000101011000 *
#87500
0"
0)
#88000
1"
b00000000000000000000000101011100 #
1)
b00000000000000000000000101011100 *
#88500
0"
0)
#89000
1"
b00000000000000000000000101100000 #
1)
b00000000000000000000000101100000 *
#89500
0"
0)
#90000
1"
b00000000000000000000000101100100 #
1)
b00000000000000000000000101100100 *
#90500
0"
0)
#91000
1"
b00000000000000000000000101101000 #
1)
b00000000000000000000000101101000 *
#91500
0"
0)
#92000
1"
b00000000000000000000000101101100 #
1)
b00000000000000000000000101101100 *
#92500
0"
0)
#93000
1"
b00000000000000000000000101110000 #
1)
b00000000000000000000000101110000 *
#93500
0"
0)
#94000
1"
b00000000000000000000000101110100 #
1)
b00000000000000000000000101110100 *
#94500
0"
0)
#95000
1"
b00000000000000000000000101111000 #
1)
b00000000000000000000000101111000 *
#95500
0"
0)
#96000
1"
b00000000000000000000000101111100 #
1)
b00000000000000000000000101111100 *
#96500
0"
0)
#97000
1"
b00000000000000000000000110000000 #
1)
b00000000000000000000000110000000 *
#97500
0"
0)
#98000
1"
b00000000000000000000000110000100 #
1)
b00000000000000000000000110000100 *
#98500
0"
0)
#99000
1"
b00000000000000000000000110001000 #
1)
b00000000000000000000000110001000 *
#99500
0"
0)
#100000
1"
b00000000000000000000000110001100 #
1)
b00000000000000000000000110001100 *
#100500
0"
0)
#101000
1"
b00000000000000000000000110010000 #
1)
b00000000000000000000000110010000 *
#101500
0"
0)
#102000
1"
b00000000000000000000000110010100 #
1)
b00000000000000000000000110010100 *
#102500
0"
0)
#103000
1"
b00000000000000000000000110011000 #
1)
b00000000000000000000000110011000 *
#103500
0"
0)
#104000
1"
b00000000000000000000000110011100 #
1)
b00000000000000000000000110011100 *
#104500
0"
0)
#105000
1"
b00000000000000000000000110100000 #
1)
b00000000000000000000000110100000 *
#105500
0"
0)
#106000
1"
b00000000000000000000000110100100 #
1)
b00000000000000000000000110100100 *
#106500
0"
0)
#107000
1"
b00000000000000000000000110101000 #
1)
b00000000000000000000000110101000 *
#107500
0"
0)
#108000
1"
b00000000000000000000000110101100 #
1)
b00000000000000000000000110101100 *
#108500
0"
0)
#109000
1"
b00000000000000000000000110110000 #
1)
b00000000000000000000000110110000 *
#109500
0"
0)
#110000
1"
b00000000000000000000000110110100 #
1)
b00000000000000000000000110110100 *
#110500
0"
0)
#111000
1"
b00000000000000000000000110111000 #
1)
b00000000000000000000000110111000 *
#111500
0"
0)
#112000
1"
b00000000000000000000000110111100 #
1)
b00000000000000000000000110111100 *
#112500
0"
0)
#113000
1"
b00000000000000000000000111000000 #
1)
b00000000000000000000000111000000 *
#113500
0"
0)
#114000
1"
b00000000000000000000000111000100 #
1)
b00000000000000000000000111000100 *
#114500
0"
0)
#115000
1"
b00000000000000000000000111001000 #
1)
b00000000000000000000000111001000 *
#115500
0"
0)
#116000
1"
b00000000000000000000000111001100 #
1)
b00000000000000000000000111001100 *
#116500
0"
0)
#117000
1"
b00000000000000000000000111010000 #
1)
b00000000000000000000000111010000 *
#117500
0"
0)
#118000
1"
b00000000000000000000000111010100 #
1)
b00000000000000000000000111010100 *
#118500
0"
0)
#119000
1"
b00000000000000000000000111011000 #
1)
b00000000000000000000000111011000 *
#119500
0"
0)
#120000
1"
b00000000000000000000000111011100 #
1)
b00000000000000000000000111011100 *
#120500
0"
0)
#121000
1"
b00000000000000000000000111100000 #
1)
b00000000000000000000000111100000 *
#121500
0"
0)
#122000
1"
b00000000000000000000000111100100 #
1)
b00000000000000000000000111100100 *
#122500
0"
0)
#123000
1"
b00000000000000000000000111101000 #
1)
b00000000000000000000000111101000 *
#123500
0"
0)
#124000
1"
b00000000000000000000000111101100 #
1)
b00000000000000000000000111101100 *
#124500
0"
0)
#125000
1"
b00000000000000000000000111110000 #
1)
b00000000000000000000000111110000 *
#125500
0"
0)
#126000
1"
b00000000000000000000000111110100 #
1)
b00000000000000000000000111110100 *
#126500
0"
0)
#127000
1"
b00000000000000000000000111111000 #
1)
b00000000000000000000000111111000 *
#127500
0"
0)
#128000
1"
b00000000000000000000000111111100 #
1)
b00000000000000000000000111111100 *
#128500
0"
0)
#129001
1"
b00000000000000000000000000000000 #
1)
b00000000000000000000000000000000 *
#129501
0"
0)
#130001
1"
b11011110101011011011111011101111 $
b1111 %
1&
1)
b11011110101011011011111011101111 +
b1111 ,
1-
#130501
0"
0)
#131001
1"
b0000 %
0&
b11011110101011011011111011101111 (
1)
b0000 ,
0-
b11011110101011011011111011101111 /
#131501
0"
0)
#132001
1"
1)
#132501
0"
0)
#133001
1"
b00000000000000000000000000000100 #
b11001010111111101011101010111110 $
b11001010111111101011101010111110 (
1)
b00000000000000000000000000000100 *
b11001010111111101011101010111110 +
b11001010111111101011101010111110 /
#133501
0"
0)
#134001
1"
1)
#134501
0"
0)
#135001
1"
b00000000000000000000000000001000 #
b00010010001101000101011001111000 $
b00010010001101000101011001111000 (
1)
b00000000000000000000000000001000 *
b00010010001101000101011001111000 +
b00010010001101000101011001111000 /
#135501
0"
0)
#136001
1"
1)
#136501
0"
0)
#137001
1"
b00000000000000000000000000001100 #
b10100101101001011010010110100101 $
b10100101101001011010010110100101 (
1)
b00000000000000000000000000001100 *
b10100101101001011010010110100101 +
b10100101101001011010010110100101 /
#137501
0"
0)
#138001
1"
1)
#138501
0"
0)
#139002
1"
b00000000000000000000000000000000 #
b00000000000000000000000000000000 $
b00000000000000000000000000000000 (
1)
b00000000000000000000000000000000 *
b00000000000000000000000000000000 +
b00000000000000000000000000000000 /
#139502
0"
0)
#140002
1"
b00000000000000000000000000010000 #
b10101010101110111100110011011101 $
b1111 %
1&
1)
b00000000000000000000000000010000 *
b10101010101110111100110011011101 +
b1111 ,
1-
#140502
0"
0)
#141002
1"
b00000000000000000000000011111111 $
b0001 %
b10101010101110111100110011011101 (
1)
b00000000000000000000000011111111 +
b0001 ,
b10101010101110111100110011011101 /
#141502
0"
0)
#142002
1"
b0000 %
0&
b10101010101110111100110011111111 (
1)
b0000 ,
0-
b10101010101110111100110011111111 /
#142502
0"
0)
#143002
1"
1)
#143502
0"
0)
#144003
1"
b00000000000000000000000000000000 #
b00000000000000000000000000000000 $
b00000000000000000000000000000000 (
1)
b00000000000000000000000000000000 *
b00000000000000000000000000000000 +
b00000000000000000000000000000000 /
#144503
0"
0)
#145003
1"
b00000000000000000000000100000000 $
b1111 %
1&
1)
b00000000000000000000000100000000 +
b1111 ,
1-
#145503
0"
0)
#146003
1"
b00000000000000000000000000000100 #
b00000000000000000000000100000001 $
1)
b00000000000000000000000000000100 *
b00000000000000000000000100000001 +
#146503
0"
0)
#147003
1"
b00000000000000000000000000001000 #
b00000000000000000000000100000010 $
1)
b00000000000000000000000000001000 *
b00000000000000000000000100000010 +
#147503
0"
0)
#148003
1"
b00000000000000000000000000001100 #
b00000000000000000000000100000011 $
1)
b00000000000000000000000000001100 *
b00000000000000000000000100000011 +
#148503
0"
0)
#149003
1"
b00000000000000000000000000010000 #
b00000000000000000000000100000100 $
1)
b00000000000000000000000000010000 *
b00000000000000000000000100000100 +
#149503
0"
0)
#150003
1"
b00000000000000000000000000010100 #
b00000000000000000000000100000101 $
1)
b00000000000000000000000000010100 *
b00000000000000000000000100000101 +
#150503
0"
0)
#151003
1"
b00000000000000000000000000011000 #
b00000000000000000000000100000110 $
1)
b00000000000000000000000000011000 *
b00000000000000000000000100000110 +
#151503
0"
0)
#152003
1"
b00000000000000000000000000011100 #
b00000000000000000000000100000111 $
1)
b00000000000000000000000000011100 *
b00000000000000000000000100000111 +
#152503
0"
0)
#153003
1"
b00000000000000000000000000100000 #
b00000000000000000000000100001000 $
1)
b00000000000000000000000000100000 *
b00000000000000000000000100001000 +
#153503
0"
0)
#154003
1"
b00000000000000000000000000100100 #
b00000000000000000000000100001001 $
1)
b00000000000000000000000000100100 *
b00000000000000000000000100001001 +
#154503
0"
0)
#155003
1"
b00000000000000000000000000101000 #
b00000000000000000000000100001010 $
1)
b00000000000000000000000000101000 *
b00000000000000000000000100001010 +
#155503
0"
0)
#156003
1"
b00000000000000000000000000101100 #
b00000000000000000000000100001011 $
1)
b00000000000000000000000000101100 *
b00000000000000000000000100001011 +
#156503
0"
0)
#157003
1"
b00000000000000000000000000110000 #
b00000000000000000000000100001100 $
1)
b00000000000000000000000000110000 *
b00000000000000000000000100001100 +
#157503
0"
0)
#158003
1"
b00000000000000000000000000110100 #
b00000000000000000000000100001101 $
1)
b00000000000000000000000000110100 *
b00000000000000000000000100001101 +
#158503
0"
0)
#159003
1"
b00000000000000000000000000111000 #
b00000000000000000000000100001110 $
1)
b00000000000000000000000000111000 *
b00000000000000000000000100001110 +
#159503
0"
0)
#160003
1"
b00000000000000000000000000111100 #
b00000000000000000000000100001111 $
1)
b00000000000000000000000000111100 *
b00000000000000000000000100001111 +
#160503
0"
0)
#161003
1"
b00000000000000000000000000000000 #
b0000 %
0&
b00000000000000000000000100000000 (
1)
b00000000000000000000000000000000 *
b0000 ,
0-
b00000000000000000000000100000000 /
#161503
0"
0)
#162003
1"
b00000000000000000000000000000100 #
b00000000000000000000000100000001 (
1)
b00000000000000000000000000000100 *
b00000000000000000000000100000001 /
#162503
0"
0)
#163003
1"
b00000000000000000000000000001000 #
b00000000000000000000000100000010 (
1)
b00000000000000000000000000001000 *
b00000000000000000000000100000010 /
#163503
0"
0)
#164003
1"
b00000000000000000000000000001100 #
b00000000000000000000000100000011 (
1)
b00000000000000000000000000001100 *
b00000000000000000000000100000011 /
#164503
0"
0)
#165003
1"
b00000000000000000000000000010000 #
b00000000000000000000000100000100 (
1)
b00000000000000000000000000010000 *
b00000000000000000000000100000100 /
#165503
0"
0)
#166003
1"
b00000000000000000000000000010100 #
b00000000000000000000000100000101 (
1)
b00000000000000000000000000010100 *
b00000000000000000000000100000101 /
#166503
0"
0)
#167003
1"
b00000000000000000000000000011000 #
b00000000000000000000000100000110 (
1)
b00000000000000000000000000011000 *
b00000000000000000000000100000110 /
#167503
0"
0)
#168003
1"
b00000000000000000000000000011100 #
b00000000000000000000000100000111 (
1)
b00000000000000000000000000011100 *
b00000000000000000000000100000111 /
#168503
0"
0)
#169003
1"
b00000000000000000000000000100000 #
b00000000000000000000000100001000 (
1)
b00000000000000000000000000100000 *
b00000000000000000000000100001000 /
#169503
0"
0)
#170003
1"
b00000000000000000000000000100100 #
b00000000000000000000000100001001 (
1)
b00000000000000000000000000100100 *
b00000000000000000000000100001001 /
#170503
0"
0)
#171003
1"
b00000000000000000000000000101000 #
b00000000000000000000000100001010 (
1)
b00000000000000000000000000101000 *
b00000000000000000000000100001010 /
#171503
0"
0)
#172003
1"
b00000000000000000000000000101100 #
b00000000000000000000000100001011 (
1)
b00000000000000000000000000101100 *
b00000000000000000000000100001011 /
#172503
0"
0)
#173003
1"
b00000000000000000000000000110000 #
b00000000000000000000000100001100 (
1)
b00000000000000000000000000110000 *
b00000000000000000000000100001100 /
#173503
0"
0)
#174003
1"
b00000000000000000000000000110100 #
b00000000000000000000000100001101 (
1)
b00000000000000000000000000110100 *
b00000000000000000000000100001101 /
#174503
0"
0)
#175003
1"
b00000000000000000000000000111000 #
b00000000000000000000000100001110 (
1)
b00000000000000000000000000111000 *
b00000000000000000000000100001110 /
#175503
0"
0)
#176003
1"
b00000000000000000000000000111100 #
b00000000000000000000000100001111 (
1)
b00000000000000000000000000111100 *
b00000000000000000000000100001111 /
