src/control.sv
`timescale 1ns/1ps

module control (
    // IN
    input  logic [6:0] op,
    input  logic [2:0] func3,
    input  logic [6:0] func7,
    input  logic       alu_zero,
    input  logic       alu_last_bit,  // alu_result[0] for BLT/BGE family

    // OUT
    output logic [3:0] alu_control,
    output logic [2:0] imm_source,       // 3-bit: I/S/B/J/U formats
    output logic       mem_write,
    output logic       reg_write,
    output logic       alu_source,       // 0=reg2, 1=immediate
    output logic [1:0] write_back_source,// 00=alu, 01=mem, 10=pc+4, 11=pc+imm
    output logic       pc_source,        // 1 = take branch/jump
    output logic [1:0] second_add_source // 00=pc+imm, 01=imm only(LUI), 10=rs1+imm(JALR)
);

import holy_core_pkg::*;

// ── MAIN DECODER ────────────────────────────────────────────────────────────
logic [1:0] alu_op;
logic       branch;
logic       jump;

always_comb begin
    // Safe defaults — prevent latches and avoid unintended state changes
    reg_write         = 1'b0;
    imm_source        = 3'b000;
    mem_write         = 1'b0;
    alu_op            = 2'b00;
    alu_source        = 1'b0;
    write_back_source = 2'b00;
    branch            = 1'b0;
    jump              = 1'b0;
    second_add_source = 2'b00;

    case (op)

        // LW — I-type load
        OPCODE_I_TYPE_LOAD : begin
            reg_write         = 1'b1;
            imm_source        = 3'b000;
            alu_source        = 1'b1;   // use immediate as ALU src2
            alu_op            = ALU_OP_LOAD_STORE;
            write_back_source = 2'b01;  // data memory read
        end

        // ADDI / ANDI / ORI / XORI / SLTI / SLTIU / SLLI / SRLI / SRAI — I-type ALU
        OPCODE_I_TYPE_ALU : begin
            imm_source        = 3'b000;
            alu_source        = 1'b1;   // immediate
            alu_op            = ALU_OP_MATH;
            write_back_source = 2'b00;  // alu result
            // Shift instructions encode f7 in the upper 7 bits of the immediate.
            // Only valid f7 values are accepted; invalid encodings suppress the write.
            if (func3 == F3_SLL) begin
                reg_write = (func7 == F7_NORMAL) ? 1'b1 : 1'b0;
            end else if (func3 == F3_SRL_SRA) begin
                reg_write = (func7 == F7_NORMAL || func7 == F7_ALT) ? 1'b1 : 1'b0;
            end else begin
                reg_write = 1'b1;
            end
        end

        // SW — S-type
        OPCODE_S_TYPE : begin
            imm_source = 3'b001;
            alu_source = 1'b1;
            mem_write  = 1'b1;
            alu_op     = ALU_OP_LOAD_STORE;
        end

        // ADD / SUB / AND / OR / XOR / SLT / SLTU / SLL / SRL / SRA — R-type
        OPCODE_R_TYPE : begin
            reg_write         = 1'b1;
            alu_source        = 1'b0;   // reg2
            alu_op            = ALU_OP_MATH;
            write_back_source = 2'b00;
        end

        // BEQ / BNE / BLT / BGE / BLTU / BGEU — B-type
        OPCODE_B_TYPE : begin
            imm_source        = 3'b010;
            alu_source        = 1'b0;
            alu_op            = ALU_OP_BRANCHES;
            branch            = 1'b1;
            second_add_source = 2'b00;  // pc + imm
        end

        // JAL — J-type
        OPCODE_J_TYPE : begin
            reg_write         = 1'b1;
            imm_source        = 3'b011;
            write_back_source = 2'b10;  // pc + 4 (return address)
            jump              = 1'b1;
            second_add_source = 2'b00;  // pc + imm
        end

        // JALR — I-type variant
        OPCODE_J_TYPE_JALR : begin
            reg_write         = 1'b1;
            imm_source        = 3'b000;
            alu_source        = 1'b1;
            write_back_source = 2'b10;  // pc + 4 (return address)
            jump              = 1'b1;
            second_add_source = 2'b10;  // rs1 + imm
        end

        // LUI — U-type
        OPCODE_U_TYPE_LUI : begin
            reg_write         = 1'b1;
            imm_source        = 3'b100;
            write_back_source = 2'b11;  // pc_plus_second_add (imm directly)
            second_add_source = 2'b01;  // immediate only (not added to pc)
        end

        // AUIPC — U-type
        OPCODE_U_TYPE_AUIPC : begin
            reg_write         = 1'b1;
            imm_source        = 3'b100;
            write_back_source = 2'b11;  // pc + imm
            second_add_source = 2'b00;  // pc + imm
        end

        default : begin
            // Unknown opcode — do not touch CPU or memory state
            $display("[CONTROL] Unknown opcode: %b", op);
        end
    endcase
end


// ── ALU DECODER ─────────────────────────────────────────────────────────────
always_comb begin
    case (alu_op)

        // LW / SW — always ADD for address calculation
        ALU_OP_LOAD_STORE : alu_control = ALU_ADD;

        // R-type and I-type ALU
        ALU_OP_MATH : begin
            case (func3)
                F3_ADD_SUB : begin
                    // R-type: check f7 for SUB vs ADD
                    // I-type (ADDI): always ADD (f7 field is part of immediate, not op)
                    if (op == OPCODE_R_TYPE)
                        alu_control = (func7 == F7_ALT) ? ALU_SUB : ALU_ADD;
                    else
                        alu_control = ALU_ADD;
                end
                F3_AND     : alu_control = ALU_AND;
                F3_OR      : alu_control = ALU_OR;
                F3_XOR     : alu_control = ALU_XOR;
                F3_SLT     : alu_control = ALU_SLT;
                F3_SLTU    : alu_control = ALU_SLTU;
                F3_SLL     : alu_control = ALU_SLL;
                F3_SRL_SRA : alu_control = (func7 == F7_ALT) ? ALU_SRA : ALU_SRL;
                default    : alu_control = ALU_ADD;
            endcase
        end

        // Branches — ALU performs the comparison; branch_logic_decode handles the condition
        ALU_OP_BRANCHES : begin
            case (func3)
                F3_BEQ, F3_BNE   : alu_control = ALU_SUB;  // zero flag used
                F3_BLT, F3_BGE   : alu_control = ALU_SLT;  // signed compare, last_bit used
                F3_BLTU, F3_BGEU : alu_control = ALU_SLTU; // unsigned compare, last_bit used
                default           : alu_control = ALU_SUB;
            endcase
        end

        default : alu_control = ALU_ADD;
    endcase
end


// ── PC_SOURCE — branch condition decode ─────────────────────────────────────
logic assert_branch;

always_comb begin : branch_logic_decode
    case (func3)
        F3_BEQ        : assert_branch = alu_zero    & branch;  //  rs1 == rs2
        F3_BNE        : assert_branch = ~alu_zero   & branch;  //  rs1 != rs2
        F3_BLT, F3_BLTU : assert_branch = alu_last_bit & branch; // rs1 < rs2
        F3_BGE, F3_BGEU : assert_branch = ~alu_last_bit & branch; // rs1 >= rs2
        default        : assert_branch = 1'b0;
    endcase
end

assign pc_source = assert_branch | jump;

endmodule

tb/control/dump.vcd
$version Generated by VerilatedVcd $end
$timescale 1ps $end
 $scope module $rootio $end
  $var wire 7 " op [6:0] $end
  $var wire 3 # func3 [2:0] $end
  $var wire 7 $ func7 [6:0] $end
  $var wire 1 % alu_zero $end
  $var wire 1 & alu_last_bit $end
  $var wire 4 ' alu_control [3:0] $end
  $var wire 3 ( imm_source [2:0] $end
  $var wire 1 ) mem_write $end
  $var wire 1 * reg_write $end
  $var wire 1 + alu_source $end
  $var wire 2 , write_back_source [1:0] $end
  $var wire 1 - pc_source $end
  $var wire 2 . second_add_source [1:0] $end
 $upscope $end
 $scope module control $end
  $var wire 7 / op [6:0] $end
  $var wire 3 0 func3 [2:0] $end
  $var wire 7 1 func7 [6:0] $end
  $var wire 1 2 alu_zero $end
  $var wire 1 3 alu_last_bit $end
  $var wire 4 4 alu_control [3:0] $end
  $var wire 3 5 imm_source [2:0] $end
  $var wire 1 6 mem_write $end
  $var wire 1 7 reg_write $end
  $var wire 1 8 alu_source $end
  $var wire 2 9 write_back_source [1:0] $end
  $var wire 1 : pc_source $end
  $var wire 2 ; second_add_source [1:0] $end
  $var wire 2 < alu_op [1:0] $end
  $var wire 1 = branch $end
  $var wire 1 > jump $end
  $var wire 1 ? assert_branch $end
 $upscope $end
$enddefinitions $end


#0
b0000000 "
b000 #
b0000000 $
0%
0&
b0000 '
b000 (
0)
0*
0+
b00 ,
0-
b00 .
b0000000 /
b000 0
b0000000 1
02
03
b0000 4
b000 5
06
07
08
b00 9
0:
b00 ;
b00 <
0=
0>
0?
#2000
b0000011 "
1*
1+
b01 ,
b0000011 /
17
18
b01 9
#4001
b0000000 "
0*
0+
b00 ,
b0000000 /
07
08
b00 9
#5001
b0100011 "
b001 (
1)
1+
b0100011 /
b001 5
16
18
#7002
b0000000 "
b000 (
0)
0+
b0000000 /
b000 5
06
08
#8002
b0110011 "
1*
b0110011 /
17
b10 <
#10003
b0000000 "
0*
b0000000 /
07
b00 <
#11003
b0110011 "
b0100000 $
b0001 '
1*
b0110011 /
b0100000 1
b0001 4
17
b10 <
#13004
b0000000 "
b0000000 $
b0000 '
0*
b0000000 /
b0000000 1
b0000 4
07
b00 <
#14004
b0110011 "
b111 #
b0010 '
1*
b0110011 /
b111 0
b0010 4
17
b10 <
#16005
b0000000 "
b000 #
b0000 '
0*
b0000000 /
b000 0
b0000 4
07
b00 <
#17005
b0110011 "
b110 #
b0011 '
1*
b0110011 /
b110 0
b0011 4
17
b10 <
#19006
b0000000 "
b000 #
b0000 '
0*
b0000000 /
b000 0
b0000 4
07
b00 <
#20006
b0010011 "
1*
1+
b0010011 /
17
18
b10 <
#22007
b0000000 "
0*
0+
b0000000 /
07
08
b00 <
#23007
b1100011 "
b0001 '
b010 (
b1100011 /
b0001 4
b010 5
b01 <
1=
#24007
1%
1-
12
1:
1?
#26008
b0000000 "
0%
b0000 '
b000 (
0-
b0000000 /
02
b0000 4
b000 5
0:
b00 <
0=
0?
#27008
b1100011 "
b001 #
1%
b0001 '
b010 (
b1100011 /
b001 0
12
b0001 4
b010 5
b01 <
1=
#28008
0%
1-
02
1:
1?
#30009
b0000000 "
b000 #
b0000 '
b000 (
0-
b0000000 /
b000 0
b0000 4
b000 5
0:
b00 <
0=
0?
#31009
b1100011 "
b100 #
b0101 '
b010 (
b1100011 /
b100 0
b0101 4
b010 5
b01 <
1=
#32009
1&
1-
13
1:
1?
#34010
b0000000 "
b000 #
0&
b0000 '
b000 (
0-
b0000000 /
b000 0
03
b0000 4
b000 5
0:
b00 <
0=
0?
#35010
b1101111 "
b011 (
1*
b10 ,
1-
b1101111 /
b011 5
17
b10 9
1:
1>
#37011
b0000000 "
b000 (
0*
b00 ,
0-
b0000000 /
b000 5
07
b00 9
0:
0>
#38011
b0110111 "
b100 (
1*
b11 ,
b01 .
b0110111 /
b100 5
17
b11 9
b01 ;
