src/alu.sv
`timescale 1ns/1ps

module alu (
    // IN
    input  logic [3:0]  alu_control,  // extended to 4-bit for full RV32I op set
    input  logic [31:0] src1,
    input  logic [31:0] src2,

    // OUT
    output logic [31:0] alu_result,
    output logic        zero,
    output logic        last_bit      // alu_result[0] — used by BLT/BGE branch logic
);

import holy_core_pkg::*;

wire [4:0] shamt = src2[4:0]; // shift amount is lower 5 bits of src2

always_comb begin
    case (alu_control)
        ALU_ADD  : alu_result = src1 + src2;
        ALU_SUB  : alu_result = src1 + (~src2 + 1'b1);          // src1 - src2
        ALU_AND  : alu_result = src1 & src2;
        ALU_OR   : alu_result = src1 | src2;
        ALU_XOR  : alu_result = src1 ^ src2;
        ALU_SLT  : alu_result = {31'b0, $signed(src1) < $signed(src2)}; // signed compare
        ALU_SLTU : alu_result = {31'b0, src1 < src2};            // unsigned compare
        ALU_SLL  : alu_result = src1 << shamt;
        ALU_SRL  : alu_result = src1 >> shamt;
        ALU_SRA  : alu_result = $signed(src1) >>> shamt;         // arithmetic shift
        default  : alu_result = 32'b0;
    endcase
end

assign zero     = (alu_result == 32'b0);
assign last_bit = alu_result[0];

endmodule

tb/alu/dump.vcd
$version Generated by VerilatedVcd $end
$timescale 1ps $end
 $scope module $rootio $end
  $var wire 4 " alu_control [3:0] $end
  $var wire 32 # src1 [31:0] $end
  $var wire 32 $ src2 [31:0] $end
  $var wire 32 % alu_result [31:0] $end
  $var wire 1 & zero $end
  $var wire 1 ' last_bit $end
 $upscope $end
 $scope module alu $end
  $var wire 4 ( alu_control [3:0] $end
  $var wire 32 ) src1 [31:0] $end
  $var wire 32 * src2 [31:0] $end
  $var wire 32 + alu_result [31:0] $end
  $var wire 1 , zero $end
  $var wire 1 - last_bit $end
  $var wire 5 . shamt [4:0] $end
 $upscope $end
$enddefinitions $end


#0
b0000 "
b00000000000000000000000000000000 #
b00000000000000000000000000000000 $
b00000000000000000000000000000000 %
1&
0'
b0000 (
b00000000000000000000000000000000 )
b00000000000000000000000000000000 *
b00000000000000000000000000000000 +
1,
0-
b00000 .
#1000
b01110000011001001100110011101101 #
b00110111011011001101101110011111 $
b10100111110100011010100010001100 %
0&
b01110000011001001100110011101101 )
b00110111011011001101101110011111 *
b10100111110100011010100010001100 +
0,
b11111 .
#2000
b00010100111110110100011010111011 #
b10100111110111101010101001001101 $
b10111100110110011111000100001000 %
b00010100111110110100011010111011 )
b10100111110111101010101001001101 *
b10111100110110011111000100001000 +
b01101 .
#3000
b01101011000001001000111110010010 #
b11011111000101011110010111100110 $
b01001010000110100111010101111000 %
b01101011000001001000111110010010 )
b11011111000101011110010111100110 *
b01001010000110100111010101111000 +
b00110 .
#4000
b11100010001110110010011110010111 #
b11100001110011101000101011011000 $
b11000100000010011011001001101111 %
1'
b11100010001110110010011110010111 )
b11100001110011101000101011011000 *
b11000100000010011011001001101111 +
1-
b11000 .
#5000
b00011101110000010001011100110011 #
b00111100010110101100101101110000 $
b01011010000110111110001010100011 %
b00011101110000010001011100110011 )
b00111100010110101100101101110000 *
b01011010000110111110001010100011 +
b10000 .
#6000
b00111101100111110100100010111100 #
b01100110011010000111011010001001 $
b10100100000001111011111101000101 %
b00111101100111110100100010111100 )
b01100110011010000111011010001001 *
b10100100000001111011111101000101 +
b01001 .
#7000
b00111100101011100110011011101101 #
b11101000100110101000010110111111 $
b00100101010010001110110010101100 %
0'
b00111100101011100110011011101101 )
b11101000100110101000010110111111 *
b00100101010010001110110010101100 +
0-
b11111 .
#8000
b10001100101111110110011111100010 #
b01010000001001101000111010001011 $
b11011100111001011111011001101101 %
1'
b10001100101111110110011111100010 )
b01010000001001101000111010001011 *
b11011100111001011111011001101101 +
1-
b01011 .
#9000
b11001011100001010101110010010101 #
b00111110101010100011100001010111 $
b00001010001011111001010011101100 %
0'
b11001011100001010101110010010101 )
b00111110101010100011100001010111 *
b00001010001011111001010011101100 +
0-
b10111 .
#10000
b00001011110110011001111010011010 #
b00110111111110001001010000001000 $
b01000011110100100011001010100010 %
b00001011110110011001111010011010 )
b00110111111110001001010000001000 *
b01000011110100100011001010100010 +
b01000 .
#11000
b00100011000101101111101100000100 #
b01001001110111101100111010111110 $
b01101100111101011100100111000010 %
b00100011000101101111101100000100 )
b01001001110111101100111010111110 *
b01101100111101011100100111000010 +
b11110 .
#12000
b01011010111111000110111100100011 #
b10110100011010011010011001011010 $
b00001111011001100001010101111101 %
1'
b01011010111111000110111100100011 )
b10110100011010011010011001011010 *
b00001111011001100001010101111101 +
1-
b11010 .
#13000
b01010110000000001011111111011100 #
b00010010000001001010100110111000 $
b01101000000001010110100110010100 %
0'
b01010110000000001011111111011100 )
b00010010000001001010100110111000 *
b01101000000001010110100110010100 +
0-
b11000 .
#14000
b01011010001000000000000111010000 #
b11111001010010101110011101010010 $
b01010011011010101110100100100010 %
b01011010001000000000000111010000 )
b11111001010010101110011101010010 *
b01010011011010101110100100100010 +
b10010 .
#15000
b10011101010011011110100110010110 #
b00101100011001110100111100100011 $
b11001001101101010011100010111001 %
1'
b10011101010011011110100110010110 )
b00101100011001110100111100100011 *
b11001001101101010011100010111001 +
1-
b00011 .
#16000
b00010000011101000100011101110110 #
b01000110001101011111011000111001 $
b01010110101010100011110110101111 %
b00010000011101000100011101110110 )
b01000110001101011111011000111001 *
b01010110101010100011110110101111 +
b11001 .
#17000
b00101100001010111010001000111101 #
b01000111100101001011010100111001 $
b01110011110000000101011101110110 %
0'
b00101100001010111010001000111101 )
b01000111100101001011010100111001 *
b01110011110000000101011101110110 +
0-
#18000
b01100101000110001001011011010000 #
b11101110100110100010001011001110 $
b01010011101100101011100110011110 %
b01100101000110001001011011010000 )
b11101110100110100010001011001110 *
b01010011101100101011100110011110 +
b01110 .
#19000
b00110011010110010110001110000001 #
b01111111010010001100001100001111 $
b10110010101000100010011010010000 %
b00110011010110010110001110000001 )
b01111111010010001100001100001111 *
b10110010101000100010011010010000 +
b01111 .
#20000
b00111110111101100111111011001011 #
b01101000011100111001011101011110 $
b10100111011010100001011000101001 %
1'
b00111110111101100111111011001011 )
b01101000011100111001011101011110 *
b10100111011010100001011000101001 +
1-
b11110 .
#21000
b10011101001011111110110100101101 #
b11110010001011111111010110111010 $
b10001111010111111110001011100111 %
b10011101001011111110110100101101 )
b11110010001011111111010110111010 *
b10001111010111111110001011100111 +
b11010 .
#22000
b10000001110011111100100001000111 #
b10000001100110110100110111111111 $
b00000011011010110001011001000110 %
0'
b10000001110011111100100001000111 )
b10000001100110110100110111111111 *
b00000011011010110001011001000110 +
0-
b11111 .
#23000
b00100101001011110001000000100001 #
b01101011101001010010010010101000 $
b10010000110101000011010011001001 %
1'
b00100101001011110001000000100001 )
b01101011101001010010010010101000 *
b10010000110101000011010011001001 +
1-
b01000 .
#24000
b10011001011110001011000110110000 #
b10001000111001010001001101010001 $
b00100010010111011100010100000001 %
b10011001011110001011000110110000 )
b10001000111001010001001101010001 *
b00100010010111011100010100000001 +
b10001 .
#25000
b11001001011101001011111000110000 #
b01010010100000110100101111100111 $
b00011011111110000000101000010111 %
b11001001011101001011111000110000 )
b01010010100000110100101111100111 *
b00011011111110000000101000010111 +
b00111 .
#26000
b10011101101101110111011010011010 #
b10110110101001100100100000001011 $
b01010100010111011011111010100101 %
b10011101101101110111011010011010 )
b10110110101001100100100000001011 *
b01010100010111011011111010100101 +
b01011 .
#27000
b11110111110010101000010010110000 #
b11110011000010111001100000110100 $
b11101010110101100001110011100100 %
0'
b11110111110010101000010010110000 )
b11110011000010111001100000110100 *
b11101010110101100001110011100100 +
0-
b10100 .
#28000
b01111011000011010010010001011101 #
b01111011010110100000111011010011 $
b11110110011001110011001100110000 %
b01111011000011010010010001011101 )
b01111011010110100000111011010011 *
b11110110011001110011001100110000 +
b10011 .
#29000
b11101010010000101101001011111000 #
b00110100111001100100100001100110 $
b00011111001010010001101101011110 %
b11101010010000101101001011111000 )
b00110100111001100100100001100110 *
b00011111001010010001101101011110 +
b00110 .
#30000
b10000010000011011011001110111010 #
b11100011010110100001111010001010 $
b01100101011001111101001001000100 %
b10000010000011011011001110111010 )
b11100011010110100001111010001010 *
b01100101011001111101001001000100 +
b01010 .
#31000
b01111101001100111011000110111110 #
b00000111011110001001010100110100 $
b10000100101011000100011011110010 %
b01111101001100111011000110111110 )
b00000111011110001001010100110100 *
b10000100101011000100011011110010 +
b10100 .
#32000
b11111000001110000000000011111001 #
b00001100101001100101111110101000 $
b00000100110111100110000010100001 %
1'
b11111000001110000000000011111001 )
b00001100101001100101111110101000 *
b00000100110111100110000010100001 +
1-
b01000 .
#33000
b00010110110111001000000011111110 #
b11010011100110011010111000011011 $
b11101010011101100010111100011001 %
b00010110110111001000000011111110 )
b11010011100110011010111000011011 *
b11101010011101100010111100011001 +
b11011 .
#34000
b00111110111010101000011001111011 #
b10000000000110111101010100110001 $
b10111111000001100101101110101100 %
0'
b00111110111010101000011001111011 )
b10000000000110111101010100110001 *
b10111111000001100101101110101100 +
0-
b10001 .
#35000
b11000101010101001011011111111101 #
b11111011110001101001110000011011 $
b11000001000110110101010000011000 %
b11000101010101001011011111111101 )
b11111011110001101001110000011011 *
b11000001000110110101010000011000 +
b11011 .
#36000
b10001000111001011101011001000111 #
b01100010000000011110111101110111 $
b11101010111001111100010110111110 %
b10001000111001011101011001000111 )
b01100010000000011110111101110111 *
b11101010111001111100010110111110 +
b10111 .
#37000
b00010100011000000010001110100001 #
b00011011111100001000111110001011 $
b00110000010100001011001100101100 %
b00010100011000000010001110100001 )
b00011011111100001000111110001011 *
b00110000010100001011001100101100 +
b01011 .
#38000
b01011110100111010011010110011110 #
b00001101000100010001110011011011 $
b01101011101011100101001001111001 %
1'
b01011110100111010011010110011110 )
b00001101000100010001110011011011 *
b01101011101011100101001001111001 +
1-
b11011 .
#39000
b00011111001011101111110110101111 #
b10011110110011010110111100001011 $
b10111101111111000110110010111010 %
0'
b00011111001011101111110110101111 )
b10011110110011010110111100001011 *
b10111101111111000110110010111010 +
0-
b01011 .
#40000
b00110111000011110111100100000000 #
b00000010110010011100111001010100 $
b00111001110110010100011101010100 %
b00110111000011110111100100000000 )
b00000010110010011100111001010100 *
b00111001110110010100011101010100 +
b10100 .
#41000
b10110101101010001000110010001011 #
b01010001110111011101101000111101 $
b00000111100001100110011011001000 %
b10110101101010001000110010001011 )
b01010001110111011101101000111101 *
b00000111100001100110011011001000 +
b11101 .
#42000
b00011011101100011100000101110010 #
b00010110101111010001000111100110 $
b00110010011011101101001101011000 %
b00011011101100011100000101110010 )
b00010110101111010001000111100110 *
b00110010011011101101001101011000 +
b00110 .
#43000
b11010101111001010101011110101100 #
b00100100111101010001000110111101 $
b11111010110110100110100101101001 %
1'
b11010101111001010101011110101100 )
b00100100111101010001000110111101 *
b11111010110110100110100101101001 +
1-
b11101 .
#44000
b10000101110111110011010010001110 #
b00000110001111011111010001100000 $
b10001100000111010010100011101110 %
0'
b10000101110111110011010010001110 )
b00000110001111011111010001100000 *
b10001100000111010010100011101110 +
0-
b00000 .
#45000
b00011100111111011011010011001101 #
b10110101111001110000100000011101 $
b11010010111001001011110011101010 %
b00011100111111011011010011001101 )
b10110101111001110000100000011101 *
b11010010111001001011110011101010 +
b11101 .
#46000
b11100001011111101110011010000000 #
b01110001100000101111000001110100 $
b01010011000000011101011011110100 %
b11100001011111101110011010000000 )
b01110001100000101111000001110100 *
b01010011000000011101011011110100 +
b10100 .
#47000
b00011011100010110111000101100010 #
b10100110011111011110100001001011 $
b11000010000010010101100110101101 %
1'
b00011011100010110111000101100010 )
b10100110011111011110100001001011 *
b11000010000010010101100110101101 +
1-
b01011 .
#48000
b00010110100011001100111101110000 #
b01111100010100000000101101111011 $
b10010010110111001101101011101011 %
b00010110100011001100111101110000 )
b01111100010100000000101101111011 *
b10010010110111001101101011101011 +
b11011 .
#49000
b00100011001001100101010100011011 #
b01000011100010100100011111011001 $
b01100110101100001001110011110100 %
0'
b00100011001001100101010100011011 )
b01000011100010100100011111011001 *
b01100110101100001001110011110100 +
0-
b11001 .
#50000
b11101110111111011001111010101110 #
b11111000001110011010110110001000 $
b11100111001101110100110000110110 %
b11101110111111011001111010101110 )
b11111000001110011010110110001000 *
b11100111001101110100110000110110 +
b01000 .
#51000
b11001110110101001110110101011010 #
b11010111011101101001010101000101 $
b10100110010010111000001010011111 %
1'
b11001110110101001110110101011010 )
b11010111011101101001010101000101 *
b10100110010010111000001010011111 +
1-
b00101 .
#52000
b11111110111110000100110111110011 #
b01100110111100100101101000101010 $
b01100101111010101010100000011101 %
b11111110111110000100110111110011 )
b01100110111100100101101000101010 *
b01100101111010101010100000011101 +
b01010 .
#53000
b01100100011110000000110110011001 #
b01010011000001110110011001000011 $
b10110111011111110111001111011100 %
0'
b01100100011110000000110110011001 )
b01010011000001110110011001000011 *
b10110111011111110111001111011100 +
0-
b00011 .
#54000
b11100011110111011100111100111000 #
b01000111001101011000110000001111 $
b00101011000100110101101101000111 %
1'
b11100011110111011100111100111000 )
b01000111001101011000110000001111 *
b00101011000100110101101101000111 +
1-
b01111 .
#55000
b11110110100010100100001101101110 #
b00000111001010001101001000001110 $
b11111101101100110001010101111100 %
0'
b11110110100010100100001101101110 )
b00000111001010001101001000001110 *
b11111101101100110001010101111100 +
0-
b01110 .
#56000
b00011101001110101111111001010111 #
b01111110010100100110101100101000 $
b10011011100011010110100101111111 %
1'
b00011101001110101111111001010111 )
b01111110010100100110101100101000 *
b10011011100011010110100101111111 +
1-
b01000 .
#57000
b01100110101010001011000011001100 #
b01111111001011001111110101100110 $
b11100101110101011010111000110010 %
0'
b01100110101010001011000011001100 )
b01111111001011001111110101100110 *
b11100101110101011010111000110010 +
0-
b00110 .
#58000
b00101100001111010000011101100110 #
b01001000100001010011100001011011 $
b01110100110000100011111111000001 %
1'
b00101100001111010000011101100110 )
b01001000100001010011100001011011 *
b01110100110000100011111111000001 +
1-
b11011 .
#59000
b00101000011101110101000000100000 #
b11101101011111000011101100010111 $
b00010101111100111000101100110111 %
b00101000011101110101000000100000 )
b11101101011111000011101100010111 *
b00010101111100111000101100110111 +
b10111 .
#60000
b10100101111111110101100101001101 #
b01111000101010110101110000101001 $
b00011110101010101011010101110110 %
0'
b10100101111111110101100101001101 )
b01111000101010110101110000101001 *
b00011110101010101011010101110110 +
0-
b01001 .
#61000
b00011100010000101000010011110100 #
b01101111100111001110100011000100 $
b10001011110111110110110110111000 %
b00011100010000101000010011110100 )
b01101111100111001110100011000100 *
b10001011110111110110110110111000 +
b00100 .
#62000
b00001100011000010100010001111101 #
b00000001011010100001101111001010 $
b00001101110010110110000001000111 %
1'
b00001100011000010100010001111101 )
b00000001011010100001101111001010 *
b00001101110010110110000001000111 +
1-
b01010 .
#63000
b00101111001001101110111110000111 #
b11001111111001001011011010011111 $
b11111111000010111010011000100110 %
0'
b00101111001001101110111110000111 )
b11001111111001001011011010011111 *
b11111111000010111010011000100110 +
0-
b11111 .
#64000
b01001010101010100110101010011100 #
b00000101101101100000000011110011 $
b01010000011000000110101110001111 %
1'
b01001010101010100110101010011100 )
b00000101101101100000000011110011 *
b01010000011000000110101110001111 +
1-
b10011 .
#65000
b10001101100101010001111000011110 #
b10001011111011010010110111100011 $
b00011001100000100100110000000001 %
b10001101100101010001111000011110 )
b10001011111011010010110111100011 *
b00011001100000100100110000000001 +
b00011 .
#66000
b11011101011001011111010001100011 #
b01100000000001001100111000000001 $
b00111101011010101100001001100100 %
0'
b11011101011001011111010001100011 )
b01100000000001001100111000000001 *
b00111101011010101100001001100100 +
0-
b00001 .
#67000
b01001001110111100101100100010111 #
b00000000010010000000101101100010 $
b01001010001001100110010001111001 %
1'
b01001001110111100101100100010111 )
b00000000010010000000101101100010 *
b01001010001001100110010001111001 +
1-
b00010 .
#68000
b01100101011011010101010100010100 #
b00100111010111100011101101101000 $
b10001100110010111001000001111100 %
0'
b01100101011011010101010100010100 )
b00100111010111100011101101101000 *
b10001100110010111001000001111100 +
0-
b01000 .
#69000
b00100010000110001000001010111111 #
b00010001101001100110111001111001 $
b00110011101111101111000100111000 %
b00100010000110001000001010111111 )
b00010001101001100110111001111001 *
b00110011101111101111000100111000 +
b11001 .
#70000
b10110010010100111101110100111010 #
b01001001111010110111101110110011 $
b11111100001111110101100011101101 %
1'
b10110010010100111101110100111010 )
b01001001111010110111101110110011 *
b11111100001111110101100011101101 +
1-
b10011 .
#71000
b10100101010100010110101011000001 #
b01010111101011001111101010101011 $
b11111100111111100110010101101100 %
0'
b10100101010100010110101011000001 )
b01010111101011001111101010101011 *
b11111100111111100110010101101100 +
0-
b01011 .
#72000
b00111111011001100110000001111110 #
b01101011110111100110010110110010 $
b10101011010001001100011000110000 %
b00111111011001100110000001111110 )
b01101011110111100110010110110010 *
b10101011010001001100011000110000 +
b10010 .
#73000
b11111111101001000100010011110100 #
b11011101100001001110111111001111 $
b11011101001010010011010011000011 %
1'
b11111111101001000100010011110100 )
b11011101100001001110111111001111 *
b11011101001010010011010011000011 +
1-
b01111 .
#74000
b10110111001010101100001111001011 #
b10011000011101010010001010100000 $
b01001111100111111110011001101011 %
b10110111001010101100001111001011 )
b10011000011101010010001010100000 *
b01001111100111111110011001101011 +
b00000 .
#75000
b01000101001111110100000011000011 #
b01011100111000010110111000000111 $
b10100010001000001010111011001010 %
0'
b01000101001111110100000011000011 )
b01011100111000010110111000000111 *
b10100010001000001010111011001010 +
0-
b00111 .
#76000
b00101111101110101110101000110001 #
b11110000110001010111111100011111 $
b00100000100000000110100101010000 %
b00101111101110101110101000110001 )
b11110000110001010111111100011111 *
b00100000100000000110100101010000 +
b11111 .
#77000
b01101000000100001001011101111110 #
b01100010001011101011011110101010 $
b11001010001111110100111100101000 %
b01101000000100001001011101111110 )
b01100010001011101011011110101010 *
b11001010001111110100111100101000 +
b01010 .
#78000
b00100000001101001010100100011101 #
b00101011101101101000010101010100 $
b01001011111010110010111001110001 %
1'
b00100000001101001010100100011101 )
b00101011101101101000010101010100 *
b01001011111010110010111001110001 +
1-
b10100 .
#79000
b10000100010100111000010101010011 #
b10100111001011001111000001110101 $
b00101011100000000111010111001000 %
0'
b10000100010100111000010101010011 )
b10100111001011001111000001110101 *
b00101011100000000111010111001000 +
0-
b10101 .
#80000
b01000000001110110100100101100101 #
b11111100001111110100000011101010 $
b00111100011110101000101001001111 %
1'
b01000000001110110100100101100101 )
b11111100001111110100000011101010 *
b00111100011110101000101001001111 +
1-
b01010 .
#81000
b10110010011011001101001000110000 #
b00000111000110001111110110000110 $
b10111001100001011100111110110110 %
0'
b10110010011011001101001000110000 )
b00000111000110001111110110000110 *
b10111001100001011100111110110110 +
0-
b00110 .
#82000
b11001001000101110010101101011101 #
b01101111010100111110001101101011 $
b00111000011010110000111011001000 %
b11001001000101110010101101011101 )
b01101111010100111110001101101011 *
b00111000011010110000111011001000 +
b01011 .
#83000
b10111111001001111001110111011010 #
b01001100111001010111111001111110 $
b00001100000011010001110001011000 %
b10111111001001111001110111011010 )
b01001100111001010111111001111110 *
b00001100000011010001110001011000 +
b11110 .
#84000
b00011001011010000010000000011110 #
b11100010011010110010011111100101 $
b11111011110100110100100000000011 %
1'
b00011001011010000010000000011110 )
b11100010011010110010011111100101 *
b11111011110100110100100000000011 +
1-
b00101 .
#85000
b00110110110001000010010111011110 #
b11100101111100100010000100101001 $
b00011100101101100100011100000111 %
b00110110110001000010010111011110 )
b11100101111100100010000100101001 *
b00011100101101100100011100000111 +
b01001 .
#86000
b00101000000000010001111111111101 #
b11110011011000001100010011000101 $
b00011011011000011110010011000010 %
0'
b00101000000000010001111111111101 )
b11110011011000001100010011000101 *
b00011011011000011110010011000010 +
0-
b00101 .
#87000
b00000001110010010001010100111011 #
b01000010111011000000111100001001 $
b01000100101101010010010001000100 %
b00000001110010010001010100111011 )
b01000010111011000000111100001001 *
b01000100101101010010010001000100 +
b01001 .
#88000
b10011011010011101011001111100100 #
b11110000000111100011011110111001 $
b10001011011011001110101110011101 %
1'
b10011011010011101011001111100100 )
b11110000000111100011011110111001 *
b10001011011011001110101110011101 +
1-
b11001 .
#89000
b11001110000011000111110000100111 #
b11001101011001110011100011001011 $
b10011011011100111011010011110010 %
0'
b11001110000011000111110000100111 )
b11001101011001110011100011001011 *
b10011011011100111011010011110010 +
0-
b01011 .
#90000
b01111000110101100011101100001011 #
b11000110100111100011000110000001 $
b00111111011101000110110010001100 %
b01111000110101100011101100001011 )
b11000110100111100011000110000001 *
b00111111011101000110110010001100 +
b00001 .
#91000
b00111001001100111000010000011100 #
b10001101101100111110011100101101 $
b11000110111001110110101101001001 %
1'
b00111001001100111000010000011100 )
b10001101101100111110011100101101 *
b11000110111001110110101101001001 +
1-
b01101 .
#92000
b01101110001010000101011001001101 #
b00111100000001000000001111011100 $
b10101010001011000101101000101001 %
b01101110001010000101011001001101 )
b00111100000001000000001111011100 *
b10101010001011000101101000101001 +
b11100 .
#93000
b11100010011010110011111001110100 #
b11111000001010001000000111011001 $
b11011010100100111100000001001101 %
b11100010011010110011111001110100 )
b11111000001010001000000111011001 *
b11011010100100111100000001001101 +
b11001 .
#94000
b00000111101010010011111011010101 #
b00010101000100000100101111000101 $
b00011100101110011000101010011010 %
0'
b00000111101010010011111011010101 )
b00010101000100000100101111000101 *
b00011100101110011000101010011010 +
0-
b00101 .
#95000
b11111100100000101001100110101111 #
b01100100001000111100011011011011 $
b01100000101001100110000010001010 %
b11111100100000101001100110101111 )
b01100100001000111100011011011011 *
b01100000101001100110000010001010 +
b11011 .
#96000
b00010100110101100001000101100011 #
b01001001110011100101101110111111 $
b01011110101001000110110100100010 %
b00010100110101100001000101100011 )
b01001001110011100101101110111111 *
b01011110101001000110110100100010 +
b11111 .
#97000
b11110000001111111001011001101101 #
b10011100101001000000000010100011 $
b10001100111000111001011100010000 %
b11110000001111111001011001101101 )
b10011100101001000000000010100011 *
b10001100111000111001011100010000 +
b00011 .
#98000
b10111010101100000011110101111110 #
b01011100111111011111101110000011 $
b00010111101011100011100100000001 %
1'
b10111010101100000011110101111110 )
b01011100111111011111101110000011 *
b00010111101011100011100100000001 +
1-
#99000
b00100111000111000101000001111010 #
b00000101110101100110110001100101 $
b00101100111100101011110011011111 %
b00100111000111000101000001111010 )
b00000101110101100110110001100101 *
b00101100111100101011110011011111 +
b00101 .
#100000
b11010000100000110101001000101000 #
b11011101011100000011000100010010 $
b10101101111100111000001100111010 %
0'
b11010000100000110101001000101000 )
b11011101011100000011000100010010 *
b10101101111100111000001100111010 +
0-
b10010 .
#101000
b11000101011011110001100111000001 #
b01011001100101001010110101111001 $
b00011111000000111100011100111010 %
b11000101011011110001100111000001 )
b01011001100101001010110101111001 *
b00011111000000111100011100111010 +
b11001 .
#102000
b01100001011110000100100001101001 #
b10101000101010100111100110011011 $
b00001010001000101100001000000100 %
b01100001011110000100100001101001 )
b10101000101010100111100110011011 *
b00001010001000101100001000000100 +
b11011 .
#103000
b01001011000110011111001010011001 #
b00000110011111000100010101000111 $
b01010001100101100011011111100000 %
b01001011000110011111001010011001 )
b00000110011111000100010101000111 *
b01010001100101100011011111100000 +
b00111 .
#104000
b00110010001000110101011100110111 #
b01101110110011111010101011100100 $
b10100000111100110000001000011011 %
1'
b00110010001000110101011100110111 )
b01101110110011111010101011100100 *
b10100000111100110000001000011011 +
1-
b00100 .
#105000
b01010101000000011010101010101110 #
b11101010101010111001001111101011 $
b00111111101011010011111010011001 %
b01010101000000011010101010101110 )
b11101010101010111001001111101011 *
b00111111101011010011111010011001 +
b01011 .
#106000
b10011100101011010110100001111001 #
b01101011110100101000100000011100 $
b00001000011111111111000010010101 %
b10011100101011010110100001111001 )
b01101011110100101000100000011100 *
b00001000011111111111000010010101 +
b11100 .
#107000
b01100001100010110110100101101000 #
b00000000000111111110111010001001 $
b01100001101010110101011111110001 %
b01100001100010110110100101101000 )
b00000000000111111110111010001001 *
b01100001101010110101011111110001 +
b01001 .
#108000
b11110001101000000101100110110111 #
b11110101010001011101011111111011 $
b11100110111001100011000110110010 %
0'
b11110001101000000101100110110111 )
b11110101010001011101011111111011 *
b11100110111001100011000110110010 +
0-
b11011 .
#109000
b00100100011011100100011110001000 #
b00001000011010110101011011110111 $
b00101100110110011001111001111111 %
1'
b00100100011011100100011110001000 )
b00001000011010110101011011110111 *
b00101100110110011001111001111111 +
1-
b10111 .
#110000
b10101010110111110010000100101100 #
b11010000110110011111100001101110 $
b01111011101110010001100110011010 %
0'
b10101010110111110010000100101100 )
b11010000110110011111100001101110 *
b01111011101110010001100110011010 +
0-
b01110 .
#111000
b11101100111111111010000000010100 #
b10011101000110111100101001111100 $
b10001010000110110110101010010000 %
b11101100111111111010000000010100 )
b10011101000110111100101001111100 *
b10001010000110110110101010010000 +
b11100 .
#112000
b11111000111101001101101101101010 #
b00000010110011111010100111100110 $
b11111011110001001000010101010000 %
b11111000111101001101101101101010 )
b00000010110011111010100111100110 *
b11111011110001001000010101010000 +
b00110 .
#113000
b11111100110111101110010110111111 #
b10100010010110110111011011011001 $
b10011111001110100101110010011000 %
b11111100110111101110010110111111 )
b10100010010110110111011011011001 *
b10011111001110100101110010011000 +
b11001 .
#114000
b10100101001111010101111001010100 #
b10100000010101011100011010110000 $
b01000101100100110010010100000100 %
b10100101001111010101111001010100 )
b10100000010101011100011010110000 *
b01000101100100110010010100000100 +
b10000 .
#115000
b00111101100101111111010001001010 #
b01010101100100011000000000001100 $
b10010011001010010111010001010110 %
b00111101100101111111010001001010 )
b01010101100100011000000000001100 *
b10010011001010010111010001010110 +
b01100 .
#116000
b10010111000001010000001100001000 #
b01011011101000000111011001101100 $
b11110010101001010111100101110100 %
b10010111000001010000001100001000 )
b01011011101000000111011001101100 *
b11110010101001010111100101110100 +
#117000
b00110010101101000001010101001000 #
b00111011010101101010011110110101 $
b01101110000010101011110011111101 %
1'
b00110010101101000001010101001000 )
b00111011010101101010011110110101 *
b01101110000010101011110011111101 +
1-
b10101 .
#118000
b01101111001010011010110101100110 #
b00101010100110110110111101000101 $
b10011001110001010001110010101011 %
b01101111001010011010110101100110 )
b00101010100110110110111101000101 *
b10011001110001010001110010101011 +
b00101 .
#119000
b00111101111100111111001100110110 #
b00010001110000010010000100100010 $
b01001111101101010001010001011000 %
0'
b00111101111100111111001100110110 )
b00010001110000010010000100100010 *
b01001111101101010001010001011000 +
0-
b00010 .
#120000
b01101111010000000111100111010000 #
b10111110110111101010011001001001 $
b00101110000111110010000000011001 %
1'
b01101111010000000111100111010000 )
b10111110110111101010011001001001 *
b00101110000111110010000000011001 +
1-
b01001 .
#121000
b10101100100110010100110100111000 #
b11110000001100011011111101010101 $
b10011100110010110000110010001101 %
b10101100100110010100110100111000 )
b11110000001100011011111101010101 *
b10011100110010110000110010001101 +
b10101 .
#122000
b11001100110011000001000000001011 #
b11010010010100001010110101100100 $
b10011111000111001011110101101111 %
b11001100110011000001000000001011 )
b11010010010100001010110101100100 *
b10011111000111001011110101101111 +
b00100 .
#123000
b10100110111110000001001000110000 #
b01000010101101110111011101011011 $
b11101001101011111000100110001011 %
b10100110111110000001001000110000 )
b01000010101101110111011101011011 *
b11101001101011111000100110001011 +
b11011 .
#124000
b11000000000010110100010111001011 #
b00110011101101001111100000000111 $
b11110011110000000011110111010010 %
0'
b11000000000010110100010111001011 )
b00110011101101001111100000000111 *
b11110011110000000011110111010010 +
0-
b00111 .
#125000
b10001101111110100110111100110101 #
b11111100011110101010101110101100 $
b10001010011101010001101011100001 %
1'
b10001101111110100110111100110101 )
b11111100011110101010101110101100 *
b10001010011101010001101011100001 +
1-
b01100 .
#126000
b10111101010111111101110001111001 #
b00110110010010000111100101000110 $
b11110011101010000101010110111111 %
b10111101010111111101110001111001 )
b00110110010010000111100101000110 *
b11110011101010000101010110111111 +
b00110 .
#127000
b01001010000110110100010111001001 #
b11111001110000010110100110111010 $
b01000011110111001010111110000011 %
b01001010000110110100010111001001 )
b11111001110000010110100110111010 *
b01000011110111001010111110000011 +
b11010 .
#128000
b00001001101010101001001011110111 #
b01000100001110111110001101100011 $
b01001101111001100111011001011010 %
0'
b00001001101010101001001011110111 )
b01000100001110111110001101100011 *
b01001101111001100111011001011010 +
0-
b00011 .
#129000
b10000000010100010100001001110101 #
b11000100000000110101011011100010 $
b01000100010101001001100101010111 %
1'
b10000000010100010100001001110101 )
b11000100000000110101011011100010 *
b01000100010101001001100101010111 +
1-
b00010 .
#130000
b00000010100000101100111011110001 #
b10111111111010000000000011000111 $
b11000010011010101100111110111000 %
0'
b00000010100000101100111011110001 )
b10111111111010000000000011000111 *
b11000010011010101100111110111000 +
0-
b00111 .
#131000
b11100001010001100010010110100101 #
b00011100000010001100100101010100 $
b11111101010011101110111011111001 %
1'
b11100001010001100010010110100101 )
b00011100000010001100100101010100 *
b11111101010011101110111011111001 +
1-
b10100 .
#132000
b11100001100001011111000011001001 #
b11101011010001000001101111110001 $
b11001100110010100000110010111010 %
0'
b11100001100001011111000011001001 )
b11101011010001000001101111110001 *
b11001100110010100000110010111010 +
0-
b10001 .
#133000
b00001100001011011100001111110010 #
b11100001111010100101110101101110 $
b11101110000110000010000101100000 %
b00001100001011011100001111110010 )
b11100001111010100101110101101110 *
b11101110000110000010000101100000 +
b01110 .
#134000
b11001011100000100010010000011101 #
b10101011011000000010101101000010 $
b01110110111000100100111101011111 %
1'
b11001011100000100010010000011101 )
b10101011011000000010101101000010 *
b01110110111000100100111101011111 +
1-
b00010 .
#135000
b01101101111111010000101101110011 #
b11101010011100011000100101100111 $
b01011000011011101001010011011010 %
0'
b01101101111111010000101101110011 )
b11101010011100011000100101100111 *
b01011000011011101001010011011010 +
0-
b00111 .
