src/signext.sv
`timescale 1ns/1ps

module signext (
    // IN
    input  logic [24:0] raw_src,     // instruction[31:7]
    input  logic [2:0]  imm_source,  // 3-bit: selects immediate format

    // OUT
    output logic [31:0] immediate
);

/*
 * Immediate formats (RISC-V ISA Vol.I, Section 2.3):
 *
 *  raw_src bit index refers to instruction bits [31:7], so:
 *    raw_src[24] = inst[31]  (sign bit for all formats)
 *    raw_src[23:18] = inst[30:25]
 *    raw_src[17:13] = inst[24:20]
 *    raw_src[12:8]  = inst[19:15]  (rs1 field — not part of imm)
 *    raw_src[7:5]   = inst[14:12]  (funct3 — not part of imm)
 *    raw_src[4:0]   = inst[11:7]   (rd / lower S-imm bits)
 */

always_comb begin
    case (imm_source)

        // I-type: imm[11:0] = inst[31:20]
        3'b000 : immediate = {{20{raw_src[24]}}, raw_src[24:13]};

        // S-type: imm[11:5] = inst[31:25], imm[4:0] = inst[11:7]
        3'b001 : immediate = {{20{raw_src[24]}}, raw_src[24:18], raw_src[4:0]};

        // B-type: imm[12|10:5] = inst[31|30:25], imm[4:1|11] = inst[11:8|7], imm[0]=0
        3'b010 : immediate = {{20{raw_src[24]}}, raw_src[0], raw_src[23:18], raw_src[4:1], 1'b0};

        // J-type: imm[20|10:1|11|19:12] = inst[31|30:21|20|19:12], imm[0]=0
        3'b011 : immediate = {{12{raw_src[24]}}, raw_src[12:5], raw_src[13], raw_src[23:14], 1'b0};

        // U-type: imm[31:12] = inst[31:12], imm[11:0] = 0
        3'b100 : immediate = {raw_src[24:5], 12'b0};

        default: immediate = 32'b0;
    endcase
end

endmodule

tb/signext/dump.vcd
$version Generated by VerilatedVcd $end
$timescale 1ps $end
 $scope module $rootio $end
  $var wire 25 " raw_src [24:0] $end
  $var wire 3 # imm_source [2:0] $end
  $var wire 32 $ immediate [31:0] $end
 $upscope $end
 $scope module signext $end
  $var wire 25 % raw_src [24:0] $end
  $var wire 3 & imm_source [2:0] $end
  $var wire 32 ' immediate [31:0] $end
 $upscope $end
$enddefinitions $end


#0
b0000000000000000000000000 "
b000 #
b00000000000000000000000000000000 $
b0000000000000000000000000 %
b000 &
b00000000000000000000000000000000 '
#1000
b0000011110111010101010101 "
b00000000000000000000000001111011 $
b0000011110111010101010101 %
b00000000000000000000000001111011 '
#3001
b1111110101101010101010101 "
b11111111111111111111111111010110 $
b1111110101101010101010101 %
b11111111111111111111111111010110 '
#5002
b1111101011000100010111110 "
b11111111111111111111111110101100 $
b1111101011000100010111110 %
b11111111111111111111111110101100 '
#7002
b0110000001010001101111011 "
b00000000000000000000011000000101 $
b0110000001010001101111011 %
b00000000000000000000011000000101 '
#9002
b1101000100011100111100010 "
b11111111111111111111110100010001 $
b1101000100011100111100010 %
b11111111111111111111110100010001 '
#11002
b1101001101101010100110001 "
b11111111111111111111110100110110 $
b1101001101101010100110001 %
b11111111111111111111110100110110 '
#13002
b0101011000101000010000010 "
b00000000000000000000010101100010 $
b0101011000101000010000010 %
b00000000000000000000010101100010 '
#15002
b1100111010001111011101111 "
b11111111111111111111110011101000 $
b1100111010001111011101111 %
b11111111111111111111110011101000 '
#17002
b1010011010100111010001010 "
b11111111111111111111101001101010 $
b1010011010100111010001010 %
b11111111111111111111101001101010 '
#19002
b1111110001111100101001011 "
b11111111111111111111111111000111 $
b1111110001111100101001011 %
b11111111111111111111111111000111 '
#21002
b1110111011001010011001111 "
b11111111111111111111111011101100 $
b1110111011001010011001111 %
b11111111111111111111111011101100 '
#23002
b0010100001011010100111000 "
b00000000000000000000001010000101 $
b0010100001011010100111000 %
b00000000000000000000001010000101 '
#25002
b0001011111101001110100001 "
b00000000000000000000000101111110 $
b0001011111101001110100001 %
b00000000000000000000000101111110 '
#27002
b1000100011001111100100011 "
b11111111111111111111100010001100 $
b1000100011001111100100011 %
b11111111111111111111100010001100 '
#29002
b1010100101000110010111010 "
b11111111111111111111101010010100 $
b1010100101000110010111010 %
b11111111111111111111101010010100 '
#31002
b1010001011000011010000110 "
b11111111111111111111101000101100 $
b1010001011000011010000110 %
b11111111111111111111101000101100 '
#33002
b1110100000101100010010100 "
b11111111111111111111111010000010 $
b1110100000101100010010100 %
b11111111111111111111111010000010 '
#35002
b0001111100100010011101010 "
b00000000000000000000000111110010 $
b0001111100100010011101010 %
b00000000000000000000000111110010 '
#37002
b1101010110001100000111011 "
b11111111111111111111110101011000 $
b1101010110001100000111011 %
b11111111111111111111110101011000 '
#39002
b1011000101100111101111110 "
b11111111111111111111101100010110 $
b1011000101100111101111110 %
b11111111111111111111101100010110 '
#41002
b1000100000001110101001010 "
b11111111111111111111100010000000 $
b1000100000001110101001010 %
b11111111111111111111100010000000 '
#43002
b1001100000000100111011000 "
b11111111111111111111100110000000 $
b1001100000000100111011000 %
b11111111111111111111100110000000 '
#45002
b0101101100111011001101101 "
b00000000000000000000010110110011 $
b0101101100111011001101101 %
b00000000000000000000010110110011 '
#47002
b1100111000101001000101111 "
b11111111111111111111110011100010 $
b1100111000101001000101111 %
b11111111111111111111110011100010 '
#49002
b0111011100000011110000001 "
b00000000000000000000011101110000 $
b0111011100000011110000001 %
b00000000000000000000011101110000 '
#51002
b0100001011100001100000011 "
b00000000000000000000010000101110 $
b0100001011100001100000011 %
b00000000000000000000010000101110 '
#53002
b0100001010011101000100011 "
b00000000000000000000010000101001 $
b0100001010011101000100011 %
b00000000000000000000010000101001 '
#55002
b1010010001100111100000001 "
b11111111111111111111101001000110 $
b1010010001100111100000001 %
b11111111111111111111101001000110 '
#57002
b0100010111101101111111111 "
b00000000000000000000010001011110 $
b0100010111101101111111111 %
b00000000000000000000010001011110 '
#59002
b1111011011111101110100100 "
b11111111111111111111111101101111 $
b1111011011111101110100100 %
b11111111111111111111111101101111 '
#61002
b1111000010001000111010101 "
b11111111111111111111111100001000 $
b1111000010001000111010101 %
b11111111111111111111111100001000 '
#63002
b1000100011000100010111010 "
b11111111111111111111100010001100 $
b1000100011000100010111010 %
b11111111111111111111100010001100 '
#65002
b0111100100001100010110101 "
b00000000000000000000011110010000 $
b0111100100001100010110101 %
b00000000000000000000011110010000 '
#67002
b1000100011001001111000110 "
b11111111111111111111100010001100 $
b1000100011001001111000110 %
b11111111111111111111100010001100 '
#69002
b0001001000100101111100111 "
b00000000000000000000000100100010 $
b0001001000100101111100111 %
b00000000000000000000000100100010 '
#71002
b0100000111111100000010001 "
b00000000000000000000010000011111 $
b0100000111111100000010001 %
b00000000000000000000010000011111 '
#73002
b1011010110111010110010000 "
b11111111111111111111101101011011 $
b1011010110111010110010000 %
b11111111111111111111101101011011 '
#75002
b0110101101000111100101001 "
b00000000000000000000011010110100 $
b0110101101000111100101001 %
b00000000000000000000011010110100 '
#77002
b0010001110101000100111010 "
b00000000000000000000001000111010 $
b0010001110101000100111010 %
b00000000000000000000001000111010 '
#79002
b0101110101110101001111001 "
b00000000000000000000010111010111 $
b0101110101110101001111001 %
b00000000000000000000010111010111 '
#81002
b0100110101100110010101100 "
b00000000000000000000010011010110 $
b0100110101100110010101100 %
b00000000000000000000010011010110 '
#83002
b1000111001001111101011111 "
b11111111111111111111100011100100 $
b1000111001001111101011111 %
b11111111111111111111100011100100 '
#85002
b1110011110010100011010111 "
b11111111111111111111111001111001 $
b1110011110010100011010111 %
b11111111111111111111111001111001 '
#87002
b1001111100110101001011000 "
b11111111111111111111100111110011 $
b1001111100110101001011000 %
b11111111111111111111100111110011 '
#89002
b1001011100111101110111001 "
b11111111111111111111100101110011 $
b1001011100111101110111001 %
b11111111111111111111100101110011 '
#91002
b1000111001011010000101110 "
b11111111111111111111100011100101 $
b1000111001011010000101110 %
b11111111111111111111100011100101 '
#93002
b1111001010000000111001000 "
b11111111111111111111111100101000 $
b1111001010000000111001000 %
b11111111111111111111111100101000 '
#95002
b0100001010110011100000010 "
b00000000000000000000010000101011 $
b0100001010110011100000010 %
b00000000000000000000010000101011 '
#97002
b0101110111010011001010001 "
b00000000000000000000010111011101 $
b0101110111010011001010001 %
b00000000000000000000010111011101 '
#99002
b1100111110011111101010111 "
b11111111111111111111110011111001 $
b1100111110011111101010111 %
b11111111111111111111110011111001 '
#101002
b0101100010010000111000110 "
b00000000000000000000010110001001 $
b0101100010010000111000110 %
b00000000000000000000010110001001 '
#103002
b0110011100001111100101001 "
b00000000000000000000011001110000 $
b0110011100001111100101001 %
b00000000000000000000011001110000 '
#105002
b0101001011100000001101101 "
b00000000000000000000010100101110 $
b0101001011100000001101101 %
b00000000000000000000010100101110 '
#107002
b1000110000100111100101111 "
b11111111111111111111100011000010 $
b1000110000100111100101111 %
b11111111111111111111100011000010 '
#109002
b0010010111011011011001100 "
b00000000000000000000001001011101 $
b0010010111011011011001100 %
b00000000000000000000001001011101 '
#111002
b1000000011001100101100001 "
b11111111111111111111100000001100 $
b1000000011001100101100001 %
b11111111111111111111100000001100 '
#113002
b0001111010110010011110000 "
b00000000000000000000000111101011 $
b0001111010110010011110000 %
b00000000000000000000000111101011 '
#115002
b1001010010110101110111011 "
b11111111111111111111100101001011 $
b1001010010110101110111011 %
b11111111111111111111100101001011 '
#117002
b1010001010100110010100000 "
b11111111111111111111101000101010 $
b1010001010100110010100000 %
b11111111111111111111101000101010 '
#119002
b1000001111001011000101111 "
b11111111111111111111100000111100 $
b1000001111001011000101111 %
b11111111111111111111100000111100 '
#121002
b0101001000100111111011111 "
b00000000000000000000010100100010 $
b0101001000100111111011111 %
b00000000000000000000010100100010 '
#123002
b0100010111000111001100000 "
b00000000000000000000010001011100 $
b0100010111000111001100000 %
b00000000000000000000010001011100 '
#125002
b1100011011100110110101010 "
b11111111111111111111110001101110 $
b1100011011100110110101010 %
b11111111111111111111110001101110 '
#127002
b1110011110111111010101011 "
b11111111111111111111111001111011 $
b1110011110111111010101011 %
b11111111111111111111111001111011 '
#129002
b1100011100111000010101000 "
b11111111111111111111110001110011 $
b1100011100111000010101000 %
b11111111111111111111110001110011 '
#131002
b0001001011110000000110101 "
b00000000000000000000000100101111 $
b0001001011110000000110101 %
b00000000000000000000000100101111 '
#133002
b0010111100110111001111010 "
b00000000000000000000001011110011 $
b0010111100110111001111010 %
b00000000000000000000001011110011 '
#135002
b1110001000101101111110011 "
b11111111111111111111111000100010 $
b1110001000101101111110011 %
b11111111111111111111111000100010 '
#137002
b1000001000111111001000001 "
b11111111111111111111100000100011 $
b1000001000111111001000001 %
b11111111111111111111100000100011 '
#139002
b1010010010010111111000010 "
b11111111111111111111101001001001 $
b1010010010010111111000010 %
b11111111111111111111101001001001 '
#141002
b1100101110110101111111111 "
b11111111111111111111110010111011 $
b1100101110110101111111111 %
b11111111111111111111110010111011 '
#143002
b1101000110111101111011010 "
b11111111111111111111110100011011 $
b1101000110111101111011010 %
b11111111111111111111110100011011 '
#145002
b0100111100010110100100111 "
b00000000000000000000010011110001 $
b0100111100010110100100111 %
b00000000000000000000010011110001 '
#147002
b0011001111001011111000001 "
b00000000000000000000001100111100 $
b0011001111001011111000001 %
b00000000000000000000001100111100 '
#149002
b0010011110101001101101110 "
b00000000000000000000001001111010 $
b0010011110101001101101110 %
b00000000000000000000001001111010 '
#151002
b0110001001111111100110100 "
b00000000000000000000011000100111 $
b0110001001111111100110100 %
b00000000000000000000011000100111 '
#153002
b1110001010101110110100101 "
b11111111111111111111111000101010 $
b1110001010101110110100101 %
b11111111111111111111111000101010 '
#155002
b1010001010011010101010110 "
b11111111111111111111101000101001 $
b1010001010011010101010110 %
b11111111111111111111101000101001 '
#157002
b1011001011110101111000011 "
b11111111111111111111101100101111 $
b1011001011110101111000011 %
b11111111111111111111101100101111 '
#159002
b0111110101110110010011011 "
b00000000000000000000011111010111 $
b0111110101110110010011011 %
b00000000000000000000011111010111 '
#161002
b1100000000101010101111110 "
b11111111111111111111110000000010 $
b1100000000101010101111110 %
b11111111111111111111110000000010 '
#163002
b1011101001100111010010110 "
b11111111111111111111101110100110 $
b1011101001100111010010110 %
b11111111111111111111101110100110 '
#165002
b1111111110111111001001010 "
b11111111111111111111111111111011 $
b1111111110111111001001010 %
b11111111111111111111111111111011 '
#167002
b0011111011101001001100111 "
b00000000000000000000001111101110 $
b0011111011101001001100111 %
b00000000000000000000001111101110 '
#169002
b0101101001101101000011000 "
b00000000000000000000010110100110 $
b0101101001101101000011000 %
b00000000000000000000010110100110 '
#171002
b1110101011101011110111101 "
b11111111111111111111111010101110 $
b1110101011101011110111101 %
b11111111111111111111111010101110 '
#173002
b1011111110001111111010101 "
b11111111111111111111101111111000 $
b1011111110001111111010101 %
b11111111111111111111101111111000 '
#175002
b1111010110110100100011010 "
b11111111111111111111111101011011 $
b1111010110110100100011010 %
b11111111111111111111111101011011 '
#177002
b1000100100000001010101111 "
b11111111111111111111100010010000 $
b1000100100000001010101111 %
b11111111111111111111100010010000 '
#179002
b0001010000111010110000000 "
b00000000000000000000000101000011 $
b0001010000111010110000000 %
b00000000000000000000000101000011 '
#181002
b0001010000111111100100000 "
b0001010000111111100100000 %
#183002
b1111011100101001011001100 "
b11111111111111111111111101110010 $
b1111011100101001011001100 %
b11111111111111111111111101110010 '
#185002
b0101100100100100010101111 "
b00000000000000000000010110010010 $
b0101100100100100010101111 %
b00000000000000000000010110010010 '
#187002
b1010110110100100101101111 "
b11111111111111111111101011011010 $
b1010110110100100101101111 %
b11111111111111111111101011011010 '
#189002
b1101110101001101001110100 "
b11111111111111111111110111010100 $
b1101110101001101001110100 %
b11111111111111111111110111010100 '
#191002
b0010001001001010001001101 "
b00000000000000000000001000100100 $
b0010001001001010001001101 %
b00000000000000000000001000100100 '
#193002
b1110010111100011101011101 "
b11111111111111111111111001011110 $
b1110010111100011101011101 %
b11111111111111111111111001011110 '
#195002
b1010111001011001001001000 "
b11111111111111111111101011100101 $
b1010111001011001001001000 %
b11111111111111111111101011100101 '
#197002
b1101010111100011011101110 "
b11111111111111111111110101011110 $
b1101010111100011011101110 %
b11111111111111111111110101011110 '
#199002
b0110100100100000001000110 "
b00000000000000000000011010010010 $
b0110100100100000001000110 %
b00000000000000000000011010010010 '
#201002
b1100001001110010010000010 "
b11111111111111111111110000100111 $
b1100001001110010010000010 %
b11111111111111111111110000100111 '
#203002
b1000011011101010001100011 "
b11111111111111111111100001101110 $
b1000011011101010001100011 %
b11111111111111111111100001101110 '
#205002
b0010111011110101010011001 "
b00000000000000000000001011101111 $
b0010111011110101010011001 %
b00000000000000000000001011101111 '
#207002
b1100100011111011101110110 "
b11111111111111111111110010001111 $
b1100100011111011101110110 %
b11111111111111111111110010001111 '
#209002
b0010111000000010110111001 "
b00000000000000000000001011100000 $
b0010111000000010110111001 %
b00000000000000000000001011100000 '
#211002
b1011110010011100010100111 "
b11111111111111111111101111001001 $
b1011110010011100010100111 %
b11111111111111111111101111001001 '
#213002
b1110110000000010100010010 "
b11111111111111111111111011000000 $
b1110110000000010100010010 %
b11111111111111111111111011000000 '
#215002
b0001000111001000111000010 "
b00000000000000000000000100011100 $
b0001000111001000111000010 %
b00000000000000000000000100011100 '
#217002
b1000100110000001110010101 "
b11111111111111111111100010011000 $
b1000100110000001110010101 %
b11111111111111111111100010011000 '
#219002
b0001000011101011001111101 "
b00000000000000000000000100001110 $
b0001000011101011001111101 %
b00000000000000000000000100001110 '
#221002
b0011111110000100101111001 "
b00000000000000000000001111111000 $
b0011111110000100101111001 %
b00000000000000000000001111111000 '
#223002
b1010100110100001110011000 "
b11111111111111111111101010011010 $
b1010100110100001110011000 %
b11111111111111111111101010011010 '
#225002
b0111111100101000111100001 "
b00000000000000000000011111110010 $
b0111111100101000111100001 %
b00000000000000000000011111110010 '
#227002
b1001110110000010111101011 "
b11111111111111111111100111011000 $
b1001110110000010111101011 %
b11111111111111111111100111011000 '
#229002
b1001001000100101100001101 "
b11111111111111111111100100100010 $
b1001001000100101100001101 %
b11111111111111111111100100100010 '
#231002
b1001010000101011110011001 "
b11111111111111111111100101000010 $
b1001010000101011110011001 %
b11111111111111111111100101000010 '
#233002
b0101100100101010010011100 "
b00000000000000000000010110010010 $
b0101100100101010010011100 %
b00000000000000000000010110010010 '
#235002
b1100001111110111000010011 "
b11111111111111111111110000111111 $
b1100001111110111000010011 %
b11111111111111111111110000111111 '
#237002
b1110010110010101111110011 "
b11111111111111111111111001011001 $
b1110010110010101111110011 %
b11111111111111111111111001011001 '
#239002
b1001001011000001011111101 "
b11111111111111111111100100101100 $
b1001001011000001011111101 %
b11111111111111111111100100101100 '
#241002
b0010110011011000010011101 "
b00000000000000000000001011001101 $
b0010110011011000010011101 %
b00000000000000000000001011001101 '
#243002
b0111111001100101100010000 "
b00000000000000000000011111100110 $
b0111111001100101100010000 %
b00000000000000000000011111100110 '
#245002
b0101011010010101010111011 "
b00000000000000000000010101101001 $
b0101011010010101010111011 %
b00000000000000000000010101101001 '
#247002
b1001100010000101000100001 "
b11111111111111111111100110001000 $
b1001100010000101000100001 %
b11111111111111111111100110001000 '
#249002
b0000010011011110111011101 "
b00000000000000000000000001001101 $
b0000010011011110111011101 %
b00000000000000000000000001001101 '
#251002
b0110111101000000010101011 "
b00000000000000000000011011110100 $
b0110111101000000010101011 %
b00000000000000000000011011110100 '
#253002
b1011011110101010101000010 "
b11111111111111111111101101111010 $
b1011011110101010101000010 %
b11111111111111111111101101111010 '
#255002
b0001000001111111100100011 "
b00000000000000000000000100000111 $
b0001000001111111100100011 %
b00000000000000000000000100000111 '
#257002
b0000001011000110010001011 "
b00000000000000000000000000101100 $
b0000001011000110010001011 %
b00000000000000000000000000101100 '
#259002
b1111110011101110101001100 "
b11111111111111111111111111001110 $
b1111110011101110101001100 %
b11111111111111111111111111001110 '
#261002
b1001111010000110001011100 "
b11111111111111111111100111101000 $
b1001111010000110001011100 %
b11111111111111111111100111101000 '
#263002
b1010100111011100101000110 "
b11111111111111111111101010011101 $
b1010100111011100101000110 %
b11111111111111111111101010011101 '
#265002
b1111011111010011101001001 "
b11111111111111111111111101111101 $
b1111011111010011101001001 %
b11111111111111111111111101111101 '
#267002
b1110000100101111101100101 "
b11111111111111111111111000010010 $
b1110000100101111101100101 %
b11111111111111111111111000010010 '
#269002
b1010111110000101010011001 "
b11111111111111111111101011111000 $
b1010111110000101010011001 %
b11111111111111111111101011111000 '
#271002
b0010101110101010110101100 "
b00000000000000000000001010111010 $
b0010101110101010110101100 %
b00000000000000000000001010111010 '
#273002
b0011101000001000001011100 "
b00000000000000000000001110100000 $
b0011101000001000001011100 %
b00000000000000000000001110100000 '
#275002
b1111111001010101101000001 "
b11111111111111111111111111100101 $
b1111111001010101101000001 %
b11111111111111111111111111100101 '
#277002
b0100100010111110000101110 "
b00000000000000000000010010001011 $
b0100100010111110000101110 %
b00000000000000000000010010001011 '
#279002
b1000011001101110011111110 "
b11111111111111111111100001100110 $
b1000011001101110011111110 %
b11111111111111111111100001100110 '
#281002
b0100111011111110101111110 "
b00000000000000000000010011101111 $
b0100111011111110101111110 %
b00000000000000000000010011101111 '
#283002
b0010011101000001100111111 "
b00000000000000000000001001110100 $
b0010011101000001100111111 %
b00000000000000000000001001110100 '
#285002
b1010001010010011101110010 "
b11111111111111111111101000101001 $
b1010001010010011101110010 %
b11111111111111111111101000101001 '
#287002
b1010100101111001111011100 "
b11111111111111111111101010010111 $
b1010100101111001111011100 %
b11111111111111111111101010010111 '
#289002
b1000100000011001011100100 "
b11111111111111111111100010000001 $
b1000100000011001011100100 %
b11111111111111111111100010000001 '
#291002
b0000101001011111100011101 "
b00000000000000000000000010100101 $
b0000101001011111100011101 %
b00000000000000000000000010100101 '
#293002
b1000100111111001000100110 "
b11111111111111111111100010011111 $
b1000100111111001000100110 %
b11111111111111111111100010011111 '
#295002
b1101110110010111100110000 "
b11111111111111111111110111011001 $
b1101110110010111100110000 %
b11111111111111111111110111011001 '
#297002
b0011001101011111101010011 "
b00000000000000000000001100110101 $
b0011001101011111101010011 %
b00000000000000000000001100110101 '
#299002
b0101111011010100101001100 "
b00000000000000000000010111101101 $
b0101111011010100101001100 %
b00000000000000000000010111101101 '
#301002
b0011001110111011100001111 "
b00000000000000000000001100111011 $
b0011001110111011100001111 %
b00000000000000000000001100111011 '
#303002
b1110010000000101011111000 "
b11111111111111111111111001000000 $
b1110010000000101011111000 %
b11111111111111111111111001000000 '
#305002
b0100111111000101001101001 "
b00000000000000000000010011111100 $
b0100111111000101001101001 %
b00000000000000000000010011111100 '
#307002
b0111000001110011001110111 "
b00000000000000000000011100000111 $
b0111000001110011001110111 %
b00000000000000000000011100000111 '
#309002
b0101101010001011011001001 "
b00000000000000000000010110101000 $
b0101101010001011011001001 %
b00000000000000000000010110101000 '
#311002
b0010110101111001001101001 "
b00000000000000000000001011010111 $
b0010110101111001001101001 %
b00000000000000000000001011010111 '
#313002
b0011000011000000001010000 "
b00000000000000000000001100001100 $
b0011000011000000001010000 %
b00000000000000000000001100001100 '
#315002
b1001010001001001110111100 "
b11111111111111111111100101000100 $
b1001010001001001110111100 %
b11111111111111111111100101000100 '
#317002
b0101100111110001101011100 "
b00000000000000000000010110011111 $
b0101100111110001101011100 %
b00000000000000000000010110011111 '
#319002
b1100111011110000110111001 "
b11111111111111111111110011101111 $
b1100111011110000110111001 %
b11111111111111111111110011101111 '
#321002
b0111100000010101000111110 "
b00000000000000000000011110000001 $
b0111100000010101000111110 %
b00000000000000000000011110000001 '
#323002
b1101010110000111010001100 "
b11111111111111111111110101011000 $
b1101010110000111010001100 %
b11111111111111111111110101011000 '
#325002
b1101010110101000011101101 "
b11111111111111111111110101011010 $
b1101010110101000011101101 %
b11111111111111111111110101011010 '
#327002
b1111001010011111001000111 "
b11111111111111111111111100101001 $
b1111001010011111001000111 %
b11111111111111111111111100101001 '
#329002
b0000111110100110101010000 "
b00000000000000000000000011111010 $
b0000111110100110101010000 %
b00000000000000000000000011111010 '
#331002
b1011000011000101111110000 "
b11111111111111111111101100001100 $
b1011000011000101111110000 %
b11111111111111111111101100001100 '
#333002
b0001000010111110110110110 "
b00000000000000000000000100001011 $
b0001000010111110110110110 %
b00000000000000000000000100001011 '
#335002
b1010001000010001010101111 "
b11111111111111111111101000100001 $
b1010001000010001010101111 %
b11111111111111111111101000100001 '
#337002
b0100001101010101101101100 "
b00000000000000000000010000110101 $
b0100001101010101101101100 %
b00000000000000000000010000110101 '
#339002
b0100001001111010010110011 "
b00000000000000000000010000100111 $
b0100001001111010010110011 %
b00000000000000000000010000100111 '
#341002
b1001010101010100000000100 "
b11111111111111111111100101010101 $
b1001010101010100000000100 %
b11111111111111111111100101010101 '
#343002
b0111000110100000001100111 "
b00000000000000000000011100011010 $
b0111000110100000001100111 %
b00000000000000000000011100011010 '
#345002
b1101110010000001010000111 "
b11111111111111111111110111001000 $
b1101110010000001010000111 %
b11111111111111111111110111001000 '
#347002
b1001100100100111011100010 "
b11111111111111111111100110010010 $
b1001100100100111011100010 %
b11111111111111111111100110010010 '
#349002
b0110000001010011001100100 "
b00000000000000000000011000000101 $
b0110000001010011001100100 %
b00000000000000000000011000000101 '
#351002
b0110101010011000011001010 "
b00000000000000000000011010101001 $
b0110101010011000011001010 %
b00000000000000000000011010101001 '
#353002
b1000100011010100111110101 "
b11111111111111111111100010001101 $
b1000100011010100111110101 %
b11111111111111111111100010001101 '
#355002
b1110011101010100101010001 "
b11111111111111111111111001110101 $
b1110011101010100101010001 %
b11111111111111111111111001110101 '
#357002
b1000100001111101111001100 "
b11111111111111111111100010000111 $
b1000100001111101111001100 %
b11111111111111111111100010000111 '
#359002
b0111110001100000000010001 "
b00000000000000000000011111000110 $
b0111110001100000000010001 %
b00000000000000000000011111000110 '
#361002
b0101111001110111011000110 "
b00000000000000000000010111100111 $
b0101111001110111011000110 %
b00000000000000000000010111100111 '
#363002
b1111010000101101100000110 "
b11111111111111111111111101000010 $
b1111010000101101100000110 %
b11111111111111111111111101000010 '
#365002
b1010111001111011010000111 "
b11111111111111111111101011100111 $
b1010111001111011010000111 %
b11111111111111111111101011100111 '
#367002
b0010001111000001111111011 "
b00000000000000000000001000111100 $
b0010001111000001111111011 %
b00000000000000000000001000111100 '
#369002
b0011100110010010101001101 "
b00000000000000000000001110011001 $
b0011100110010010101001101 %
b00000000000000000000001110011001 '
#371002
b1000111100111100110011100 "
b11111111111111111111100011110011 $
b1000111100111100110011100 %
b11111111111111111111100011110011 '
#373002
b0110100100011111011010110 "
b00000000000000000000011010010001 $
b0110100100011111011010110 %
b00000000000000000000011010010001 '
#375002
b1111101001001111001100100 "
b11111111111111111111111110100100 $
b1111101001001111001100100 %
b11111111111111111111111110100100 '
#377002
b1101010011100011011100110 "
b11111111111111111111110101001110 $
b1101010011100011011100110 %
b11111111111111111111110101001110 '
#379002
b0011110101011101101000110 "
b00000000000000000000001111010101 $
b0011110101011101101000110 %
b00000000000000000000001111010101 '
#381002
b0001100110110010101000111 "
b00000000000000000000000110011011 $
b0001100110110010101000111 %
b00000000000000000000000110011011 '
#383002
b0001000000101110110000010 "
b00000000000000000000000100000010 $
b0001000000101110110000010 %
b00000000000000000000000100000010 '
#385002
b1001000111000000011011101 "
b11111111111111111111100100011100 $
b1001000111000000011011101 %
b11111111111111111111100100011100 '
#387002
b0001100011000001100110001 "
b00000000000000000000000110001100 $
b0001100011000001100110001 %
b00000000000000000000000110001100 '
#389002
b1000011111111100011010101 "
b11111111111111111111100001111111 $
b1000011111111100011010101 %
b11111111111111111111100001111111 '
#391002
b0011000000010110000100011 "
b00000000000000000000001100000001 $
b0011000000010110000100011 %
b00000000000000000000001100000001 '
#393002
b1101111100000010001000011 "
b11111111111111111111110111110000 $
b1101111100000010001000011 %
b11111111111111111111110111110000 '
#395002
b1000100110001101111000011 "
b11111111111111111111100010011000 $
b1000100110001101111000011 %
b11111111111111111111100010011000 '
#397002
b0011000111101111101101010 "
b00000000000000000000001100011110 $
b0011000111101111101101010 %
b00000000000000000000001100011110 '
#399002
b1101001101001110010000011 "
b11111111111111111111110100110100 $
b1101001101001110010000011 %
b11111111111111111111110100110100 '
#401002
b1110001000111010000000011 "
b11111111111111111111111000100011 $
b1110001000111010000000011 %
b11111111111111111111111000100011 '
#403002
b0011100101001011101111101 "
b00000000000000000000001110010100 $
b0011100101001011101111101 %
b00000000000000000000001110010100 '
#405003
b0110011000000000000010110 "
b001 #
b00000000000000000000011001110110 $
b0110011000000000000010110 %
b001 &
b00000000000000000000011001110110 '
#407003
b1101011000000000000001110 "
b11111111111111111111110101101110 $
b1101011000000000000001110 %
b11111111111111111111110101101110 '
#409003
b0101111000000000000001011 "
b00000000000000000000010111101011 $
b0101111000000000000001011 %
b00000000000000000000010111101011 '
#411003
b0100000000000000000011101 "
b00000000000000000000010000011101 $
b0100000000000000000011101 %
b00000000000000000000010000011101 '
#413003
b0100001000000000000000100 "
b00000000000000000000010000100100 $
b0100001000000000000000100 %
b00000000000000000000010000100100 '
#415003
b1001111000000000000000100 "
b11111111111111111111100111100100 $
b1001111000000000000000100 %
b11111111111111111111100111100100 '
#417003
b1110000000000000000000010 "
b11111111111111111111111000000010 $
b1110000000000000000000010 %
b11111111111111111111111000000010 '
#419003
b1000100000000000000000010 "
b11111111111111111111100010000010 $
b1000100000000000000000010 %
b11111111111111111111100010000010 '
#421003
b1101001000000000000011110 "
b11111111111111111111110100111110 $
b1101001000000000000011110 %
b11111111111111111111110100111110 '
#423003
b0111111000000000000000000 "
b00000000000000000000011111100000 $
b0111111000000000000000000 %
b00000000000000000000011111100000 '
#425003
b1110001000000000000001111 "
b11111111111111111111111000101111 $
b1110001000000000000001111 %
b11111111111111111111111000101111 '
#427003
b1111000000000000000000010 "
b11111111111111111111111100000010 $
b1111000000000000000000010 %
b11111111111111111111111100000010 '
#429003
b1010001000000000000000011 "
b11111111111111111111101000100011 $
b1010001000000000000000011 %
b11111111111111111111101000100011 '
#431003
b0001001000000000000001100 "
b00000000000000000000000100101100 $
b0001001000000000000001100 %
b00000000000000000000000100101100 '
#433003
b0001011000000000000010101 "
b00000000000000000000000101110101 $
b0001011000000000000010101 %
b00000000000000000000000101110101 '
#435003
b1101011000000000000000011 "
b11111111111111111111110101100011 $
b1101011000000000000000011 %
b11111111111111111111110101100011 '
#437003
b0011000000000000000010111 "
b00000000000000000000001100010111 $
b0011000000000000000010111 %
b00000000000000000000001100010111 '
#439003
b1010011000000000000010000 "
b11111111111111111111101001110000 $
b1010011000000000000010000 %
b11111111111111111111101001110000 '
#441003
b0110101000000000000011000 "
b00000000000000000000011010111000 $
b0110101000000000000011000 %
b00000000000000000000011010111000 '
#443003
b0100111000000000000011001 "
b00000000000000000000010011111001 $
b0100111000000000000011001 %
b00000000000000000000010011111001 '
#445003
b1010011000000000000000110 "
b11111111111111111111101001100110 $
b1010011000000000000000110 %
b11111111111111111111101001100110 '
#447003
b1100111000000000000010001 "
b11111111111111111111110011110001 $
b1100111000000000000010001 %
b11111111111111111111110011110001 '
#449003
b0101100000000000000001010 "
b00000000000000000000010110001010 $
b0101100000000000000001010 %
b00000000000000000000010110001010 '
#451003
b1000100000000000000011111 "
b11111111111111111111100010011111 $
b1000100000000000000011111 %
b11111111111111111111100010011111 '
#453003
b0110100000000000000001000 "
b00000000000000000000011010001000 $
b0110100000000000000001000 %
b00000000000000000000011010001000 '
#455003
b0100100000000000000000001 "
b00000000000000000000010010000001 $
b0100100000000000000000001 %
b00000000000000000000010010000001 '
#457003
b0000111000000000000011010 "
b00000000000000000000000011111010 $
b0000111000000000000011010 %
b00000000000000000000000011111010 '
#459003
b1001100000000000000001111 "
b11111111111111111111100110001111 $
b1001100000000000000001111 %
b11111111111111111111100110001111 '
#461003
b1111110000000000000011101 "
b11111111111111111111111111011101 $
b1111110000000000000011101 %
b11111111111111111111111111011101 '
#463003
b1111100000000000000010100 "
b11111111111111111111111110010100 $
b1111100000000000000010100 %
b11111111111111111111111110010100 '
